Workbook
Name Dynamic_Filter: OFFSET('PT ABC'!#REF!,,,COUNTIF('PT ABC'!#REF!,"?*"),)
Name validation_list: OFFSET('PT ABC'!#REF!,,,COUNTIF('PT ABC'!#REF!,"?*"))

Sheet Article Master
A1: S No. | B1: Details | C1: PARTICULAR | D1: Article | E1: GST % | F1: Rate | G1: Remarks | H1: Changes | K1: Input Field
A2: 1 | B2: Acrylic | C2: 3MM CLEAR ACRYLIC WITH LASER CUT | D2: 720001565 | E2: 0.18 | F2: 133
A3: =A2+1 -> 2 | B3: Acrylic | C3: 5mm Acrylic Sheet with Laser cutting | D3: 720001384 | E3: 0.18 | F3: 210
A4: =A3+1 -> 3 | B4: Acrylic | C4: Acrylic Brand Plate 1200mm X 400mm | D4: 720001181 | E4: 0.18 | F4: #N/A
A5: =A4+1 -> 4 | B5: Acrylic | C5: Acrylic Brand Plate 450mmX150MM | D5: 720001184 | E5: 0.18 | F5: #N/A
A6: =A5+1 -> 5 | B6: Acrylic | C6: Acrylic Brand Plate 750mm X 250mm | D6: 720001183 | E6: 0.18 | F6: #N/A
A7: =A6+1 -> 6 | B7: Acrylic | C7: Acrylic Brand Plate 900mm X 300mm | D7: 720001182 | E7: 0.18 | F7: #N/A
A8: =A7+1 -> 7 | B8: Adhesive | C8: Acrabond 20ml | D8: 720000030 | E8: 0.18 | F8: 40
A9: =A8+1 -> 8 | B9: Canvas | C9: Eco Solvent Print On Canvas | D9: 720001988 | E9: 0.18 | F9: 110
A10: =A9+1 -> 9 | B10: Latex | C10: Latex Print on Canvas | D10: 720002026 | E10: 0.18 | F10: 120
A11: =A10+1 -> 10 | B11: Canvas | C11: UV Print On Canvas | D11: 720002145 | E11: 0.18 | F11: 135
A12: =A11+1 -> 11 | B12: Carpet | C12: Floor Carpet | D12: 720001737 | E12: 0.12 | F12: 20
A13: =A12+1 -> 12 | B13: Vinyl | C13: Clear Vinyl Printing | D13: 720001772 | E13: 0.18 | F13: 25
A14: =A13+1 -> 13 | B14: Fabric | C14: FABRIC PRINT WITH SILICON TAPE & STITCHI | D14: 720002255 | E14: 0.18 | F14: 90
A15: =A14+1 -> 14 | B15: Flex | C15: Star Flex Eco solvent Print | D15: 720002045 | E15: 0.18 | F15: 25
A16: =A15+1 -> 15 | B16: Flex | C16: Plain Flex | D16: 720002025 | E16: 0.18 | F16: 7
A17: =A16+1 -> 16 | B17: Flex | C17: Backlit Flex Printing | D17: 720002011 | E17: 0.18 | F17: 30
A18: =A17+1 -> 17 | B18: Flex | C18: BACKLIT FLEX PRINT-16 OZ | D18: 720001775 | E18: 0.18 | F18: 25
A19: =A18+1 -> 18 | B19: Flex | C19: Frontlit Flex Printing | D19: 720002010 | E19: 0.18 | F19: 12
A20: =A19+1 -> 19 | B20: Flex | C20: Frontlit Flex Print On Branded Media | D20: 720001761 | E20: 0.18 | F20: 16
A21: =A20+1 -> 20 | B21: Flex | C21: PVC Flex | D21: 720002206 | E21: 0.18 | F21: #N/A
A22: =A21+1 -> 21 | B22: Vinyl | C22: Frosted Vinyl Cutting | D22: 720001980 | E22: 0.18 | F22: #N/A
A23: =A22+1 -> 22 | B23: Vinyl | C23: 3M Frosted Vinyl | D23: 720001345 | E23: 0.18 | F23: #N/A
A24: =A23+1 -> 23 | B24: Vinyl | C24: Lamination | D24: 720002012 | E24: 0.18 | F24: 8
A25: =A24+1 -> 24 | B25: Light/Festive | C25: TUBELIGHT,CHOWK & WIRING | D25: 720001392 | E25: 0.18 | F25: #N/A
A26: =A25+1 -> 25 | B26: Acrylic | C26: LIT Brand Plate with Vinyl | D26: 720002355 | E26: 0.18 | F26: #N/A
A27: =A26+1 -> 26 | B27: Acrylic | C27: LIT Brand Plate with Duco Paint | D27: 720002356 | E27: 0.18 | F27: #N/A
A28: =A27+1 -> 27 | B28: Metal | C28: J Hook | D28: 720001435 | E28: 0.18 | F28: #N/A
A29: =A28+1 -> 28 | B29: Metal | C29: S Hook | D29: 720001407 | E29: 0.18 | F29: #N/A
A30: =A29+1 -> 29 | B30: Digital | C30: A3 - Danglers - Digital | D30: 720002033 | E30: 0.18 | F30: NA
A31: =A30+1 -> 30 | B31: Digital | C31: A3 - Signage - Digital | D31: 720000064 | E31: 0.18 | F31: 18
A32: =A31+1 -> 31 | B32: Digital | C32: A4 - Signage - Digital | D32: 720000062 | E32: 0.18 | F32: 9
A33: =A32+1 -> 32 | B33: Digital | C33: A5 - Signage - Digital | D33: 720000063 | E33: 0.18 | F33: 6
A34: =A33+1 -> 33 | B34: Digital | C34: Shelf Talker 6" X 8" - Digital | D34: 720002024 | E34: 0.18 | F34: NA
A35: =A34+1 -> 34 | B35: Digital | C35: Wobbler Printing - Digital | D35: 720002016 | E35: 0.18 | F35: #N/A
A36: =A35+1 -> 35 | B36: Digital | C36: A2 - SIGNAGE - DIGITAL 300GSM | D36: 720001935 | E36: 0.18 | F36: #N/A
A37: =A36+1 -> 36 | B37: Offset | C37: A3 - Danglers - Offset | D37: 720002032 | E37: 0.18 | F37: #N/A
A38: =A37+1 -> 37 | B38: Offset | C38: A4 - Signage - Offset | D38: 720000057 | E38: 0.18 | F38: NA
A39: =A38+1 -> 38 | B39: Offset | C39: A5 - Signage - Offset | D39: 720000059 | E39: 0.18 | F39: NA
A40: =A39+1 -> 39 | B40: Offset | C40: Shelf Talker 2" X 5.5" - Offset | D40: 720001805 | E40: 0.18 | F40: NA
A41: =A40+1 -> 40 | B41: Offset | C41: Shelf Talker 6" X 8" - Offset | D41: 720002023 | E41: 0.18 | F41: NA
A42: =A41+1 -> 41 | B42: Offset | C42: Blank Signage Paper - A4 | D42: 720001975 | E42: 0.18 | F42: #N/A
A43: =A42+1 -> 42 | B43: Offset | C43: Blank Signage Paper - A5 | D43: 720001976 | E43: 0.18 | F43: #N/A
A44: =A43+1 -> 43 | B44: Digital | C44: A3 Sticker Paper | D44: 720001695 | E44: 0.18 | F44: 25
A45: =A44+1 -> 44 | B45: Offset | C45: A3 Generic Signage Offset | D45: 720002105 | E45: 0.18 | F45: #N/A
A46: =A45+1 -> 45 | B46: Offset | C46: A4 Generic Signage Offset | D46: 720002115 | E46: 0.18 | F46: #N/A
A47: =A46+1 -> 46 | B47: Offset | C47: A5 Generic Signage Offset | D47: 720002116 | E47: 0.18 | F47: #N/A
A48: =A47+1 -> 47 | B48: Pasting | C48: Vinyl Pasting | D48: 720002125 | E48: 0.18 | F48: 5
A49: =A48+1 -> 48 | B49: Pasting | C49: Vinyl Pasting Outstation | D49: 720002126 | E49: 0.18 | F49: 10
A50: =A49+1 -> 49 | B50: Pasting | C50: Façade Vinyl Pasting | D50: 720002127 | E50: 0.18 | F50: 8
A51: =A50+1 -> 50 | B51: Pasting | C51: Sunboard Pasting | D51: 720002129 | E51: 0.18 | F51: 5
A52: =A51+1 -> 51 | B52: Pasting | C52: Sunboard Cutting Pasting & Fitting Chgs | D52: 720002130 | E52: 0.18 | F52: 8
A53: =A52+1 -> 52 | B53: Flex | C53: Flex Mounting & Fitting Charges | D53: 720002131 | E53: 0.18 | F53: 7
A54: =A53+1 -> 53 | B54: Eco Solvent | C54: 2 side Ecosolvent Print on 3mm Sunboard | D54: 720002036 | E54: 0.18 | F54: 98
A55: =A54+1 -> 54 | B55: Eco Solvent | C55: 2 side Ecosolvent Print on 5mm Sunboard | D55: 720002035 | E55: 0.18 | F55: 110
A56: =A55+1 -> 55 | B56: Eco Solvent | C56: Eco Sol Translite Vinyl Print With Lam | D56: 720002031 | E56: 0.18 | F56: 65
A57: =A56+1 -> 56 | B57: Eco Solvent | C57: Eco Solvent Backlit Print With Lam | D57: 720002030 | E57: 0.18 | F57: 45
A58: =A57+1 -> 57 | B58: Eco Solvent | C58: Eco Solvent Backlit Print With Lam | D58: 720001758 | E58: 0.18 | F58: #N/A
A59: =A58+1 -> 58 | B59: Eco Solvent | C59: Eco Solvent Greyback Vinyl Print with La | D59: 720001998 | E59: 0.18 | F59: 48
A60: =A59+1 -> 59 | B60: Eco Solvent | C60: Eco Solvent Vinyl Print with lam 3mm Sun | D60: 720001999 | E60: 0.18 | F60: 58
A61: =A60+1 -> 60 | B61: Eco Solvent | C61: Eco Solvent Vinyl Print with lam 5mm Sun | D61: 720002000 | E61: 0.18 | F61: 70
A62: =A61+1 -> 61 | B62: Eco Solvent | C62: Eco Solvent Vinyl Printing | D62: 720001996 | E62: 0.18 | F62: 27
A63: =A62+1 -> 62 | B63: Eco Solvent | C63: Eco Solvent Vinyl Printing With Laminati | D63: 720001997 | E63: 0.18 | F63: 40
A64: =A63+1 -> 63 | B64: Eco Solvent | C64: Eco Solvent Greyback Vinyl Print | D64: 720001984 | E64: 0.18 | F64: 48
A65: =A64+1 -> 64 | B65: Eco Solvent | C65: Eco Solvent Black Back Vinyl Print | D65: 720001985 | E65: 0.18 | F65: 48
A66: =A65+1 -> 65 | B66: Eco Solvent | C66: Eco Solvent Black Back Vinyl Print With | D66: 720001986 | E66: 0.18 | F66: 48
A67: =A66+1 -> 66 | B67: Eco Solvent | C67: Eco Solvent Translite Vinyl Print | D67: 720001987 | E67: 0.18 | F67: 60
A68: =A67+1 -> 67 | B68: Flex | C68: Grey back Flex Eco solvent Print | D68: 720002046 | E68: 0.18 | F68: 25
A69: =A68+1 -> 68 | B69: Latex | C69: 2 Side Latex Print on 3mm Sunboard | D69: 720002005 | E69: 0.18 | F69: 100
A70: =A69+1 -> 69 | B70: Latex | C70: 2 Side Latex Print on 5mm Sunboard | D70: 720002007 | E70: 0.18 | F70: 120
... A78: =A77+1 -> 77 | B78: Latex | C78: Latex Vinyl Printing | D78: 720002001 | E78: 0.18 | F78: 27
A79: =A78+1 -> 78 | B79: Latex | C79: Latex Vinyl Printing without Lam | D79: 720002002 | E79: 0.18 | F79: NA
A80: =A79+1 -> 79 | B80: Latex | C80: LatexVinyl Print with Matt Lamination | D80: 720001835 | E80: 0.18 | F80: 40
A81: =A80+1 -> 80 | B81: Latex | C81: Latex Translite Print | D81: 720001989 | E81: 0.18 | F81: 80
A82: =A81+1 -> 81 | B82: Latex | C82: Latex Black Back Vinyl Print | D82: 720001990 | E82: 0.18 | F82: 40
A83: =A82+1 -> 82 | B83: Latex | C83: Latex Black Back Vinyl Print With Lam | D83: 720001991 | E83: 0.18 | F83: 49
A84: =A83+1 -> 83 | B84: Latex | C84: Latex Grey Back Vinyl | D84: 720002055 | E84: 0.18 | F84: 40
A85: =A84+1 -> 84 | B85: Latex | C85: LATEX STAR FRONTLIT BLACK BACK FLEX | D85: 720002205 | E85: 0.18 | F85: 50
A86: =A85+1 -> 85 | B86: Solvent | C86: 2 Side Solvent Print on 3mm Sunboard | D86: 720002034 | E86: 0.18 | F86: 43
A87: =A86+1 -> 86 | B87: Solvent | C87: 2 Side Solvent Print on 5mm Sunboard | D87: 720001992 | E87: 0.18 | F87: 55
A88: =A87+1 -> 87 | B88: Solvent | C88: Solvent Greyback Vinyl Print with Lam | D88: 720002022 | E88: 0.18 | F88: 31
A89: =A88+1 -> 88 | B89: Solvent | C89: Solvent Greyback Vinyl Print with Lam+3m | D89: 720001993 | E89: 0.18 | F89: 54
A90: =A89+1 -> 89 | B90: Solvent | C90: Solvent Greyback Vinyl Print with Lam+5m | D90: 720001994 | E90: 0.18 | F90: 64
A91: =A90+1 -> 90 | B91: Solvent | C91: Solvent Vinyl Print with 3mm Sunboard | D91: 720002020 | E91: 0.18 | F91: 34
... A99: =A98+1 -> 98 | B99: Solvent | C99: SOLVENT GREYBACK VINYL PRINT | D99: 720001756 | E99: 0.18 | F99: 23
A100: =A99+1 -> 99 | B100: Prop | C100: Wooden Easel Standee | D100: 720001131 | E100: 0.18 | F100: #N/A
A101: =A100+1 -> 100 | B101: Sunboard | C101: Shelf Talker 22" X 7"+3mm Black SB | D101: 720001905 | E101: 0.18 | F101: NA
A102: =A101+1 -> 101 | B102: Sunboard | C102: Sun Board 10mm | D102: 720000042 | E102: 0.18 | F102: 60
A103: =A102+1 -> 102 | B103: Sunboard | C103: Sun Board 2mm | D103: 720000029 | E103: 0.18 | F103: 14
A104: =A103+1 -> 103 | B104: Sunboard | C104: Sun Board 3 mm | D104: 720000045 | E104: 0.18 | F104: 18
A105: =A104+1 -> 104 | B105: Sunboard | C105: Sun Board 5 mm | D105: 720000046 | E105: 0.18 | F105: 30
A106: =A105+1 -> 105 | B106: Sunboard | C106: Sun Board 6mm | D106: 720000043 | E106: 0.18 | F106: 35
A107: =A106+1 -> 106 | B107: Sunboard | C107: Black Sun Board 3mm | D107: 720002215 | E107: 0.18 | F107: 35
A108: =A107+1 -> 107 | B108: Digital | C108: A2 NTR Digital Synthetic Print | D108: 720002075 | E108: 0.18 | F108: 150
A109: =A108+1 -> 108 | B109: Adhesive | C109: Adhesive Coated Tape | D109: 720000051 | E109: 0.18 | F109: 450
A110: =A109+1 -> 109 | B110: Vinyl | C110: BLACK VINYL | D110: 720001310 | E110: 0.18 | F110: #N/A
A111: =A110+1 -> 110 | B111: Vinyl | C111: GOLDEN BRUSH VINYL | D111: 720001308 | E111: 0.18 | F111: #N/A
A112: =A111+1 -> 111 | B112: Vinyl | C112: Grey Back Vinyl | D112: 720000302 | E112: 0.18 | F112: 18
A113: =A112+1 -> 112 | B113: Vinyl | C113: Plain Frosted Vinyl | D113: 720001492 | E113: 0.18 | F113: 65
A114: =A113+1 -> 113 | B114: Vinyl | C114: Plain Vinyl | D114: 720000076 | E114: 0.18 | F114: 12
...

Sheet Sheet1
B3: Unique Drop Down | C3: Dependent Drop Down
B4: Light/Festive | F4: =OFFSET($C$10,MATCH($B$4,$B$11:$B$37,0),,,COUNTIF(OFFSET($C$10,MATCH($B$4,$B$11:$B$37,0),,1,40),"?*")) -> Aluminium Profile Fabric LIT Box
M9: ='Article Master'!C6 -> Acrylic Brand Plate 750mm X 250mm
A10: Count | B10: Details
A11: =COUNTIF(Table1[Details],B11) -> 13 | B11: =IFERROR(INDEX(Table1[Details],MATCH(0,INDEX(COUNTIF($B$10:B10,Table1[Details]),),0)),"") -> Acrylic | C11: =IF(COLUMNS($C$10:C10)<=$A11,INDEX(Table1[[PARTICULAR]:[PARTICULAR]],_xlfn.AGGREGATE(15,3,(Table1[[#This Row],[Details]:[Details]]=$B11)/(Table1[[#This Row],[Details]:[Details]]=$B11)*(ROW(Table1[[Details]:[Details]])-ROW(Table1[[#Headers],[Details]])),COLUMNS($C$10:C10))),"") -> 3MM CLEAR ACRYLIC WITH LASER CUT | D11: =IF(COLUMNS($C$10:D10)<=$A11,INDEX(Table1[[PARTICULAR]:[PARTICULAR]],_xlfn.AGGREGATE(15,3,(Table1[[#This Row],[Details]:[Details]]=$B11)/(Table1[[#This Row],[Details]:[Details]]=$B11)*(ROW(Table1[[Details]:[Details]])-ROW(Table1[[#Headers],[Details]])),COLUMNS($C$10:D10))),"") -> 5mm Acrylic Sheet with Laser cutting | E11: =IF(COLUMNS($C$10:E10)<=$A11,INDEX(Table1[[PARTICULAR]:[PARTICULAR]],_xlfn.AGGREGATE(15,3,(Table1[[#This Row],[Details]:[Details]]=$B11)/(Table1[[#This Row],[Details]:[Details]]=$B11)*(ROW(Table1[[Details]:[Details]])-ROW(Table1[[#Headers],[Details]])),COLUMNS($C$10:E10))),"") -> Acrylic Brand Plate 1200mm X 400mm | F11: =IF(COLUMNS($C$10:F10)<=$A11,INDEX(Table1[[PARTICULAR]:[PARTICULAR]],_xlfn.AGGREGATE(15,3,(Table1[[#This Row],[Details]:[Details]]=$B11)/(Table1[[#This Row],[Details]:[Details]]=$B11)*(ROW(Table1[[Details]:[Details]])-ROW(Table1[[#Headers],[Details]])),COLUMNS($C$10:F10))),"") -> Acrylic Brand Plate 450mmX150MM | G11: =IF(COLUMNS($C$10:G10)<=$A11,INDEX(Table1[[PARTICULAR]:[PARTICULAR]],_xlfn.AGGREGATE(15,3,(Table1[[#This Row],[Details]:[Details]]=$B11)/(Table1[[#This Row],[Details]:[Details]]=$B11)*(ROW(Table1[[Details]:[Details]])-ROW(Table1[[#Headers],[Details]])),COLUMNS($C$10:G10))),"") -> Acrylic Brand Plate 750mm X 250mm | H11: =IF(COLUMNS($C$10:H10)<=$A11,INDEX(Table1[[PARTICULAR]:[PARTICULAR]],_xlfn.AGGREGATE(15,3,(Table1[[#This Row],[Details]:[Details]]=$B11)/(Table1[[#This Row],[Details]:[Details]]=$B11)*(ROW(Table1[[Details]:[Details]])-ROW(Table1[[#Headers],[Details]])),COLUMNS($C$10:H10))),"") -> Acrylic Brand Plate 900mm X 300mm | I11: =IF(COLUMNS($C$10:I10)<=$A11,INDEX(Table1[[PARTICULAR]:[PARTICULAR]],_xlfn.AGGREGATE(15,3,(Table1[[#This Row],[Details]:[Details]]=$B11)/(Table1[[#This Row],[Details]:[Details]]=$B11)*(ROW(Table1[[Details]:[Details]])-ROW(Table1[[#Headers],[Details]])),COLUMNS($C$10:I10))),"") -> LIT Brand Plate with Vinyl | J11: =IF(COLUMNS($C$10:J10)<=$A11,INDEX(Table1[[PARTICULAR]:[PARTICULAR]],_xlfn.AGGREGATE(15,3,(Table1[[#This Row],[Details]:[Details]]=$B11)/(Table1[[#This Row],[Details]:[Details]]=$B11)*(ROW(Table1[[Details]:[Details]])-ROW(Table1[[#Headers],[Details]])),COLUMNS($C$10:J10))),"") -> LIT Brand Plate with Duco Paint | ... CB11: =IF(COLUMNS($C$10:CB10)<=$A11,INDEX(Table1[[PARTICULAR]:[PARTICULAR]],_xlfn.AGGREGATE(15,3,(Table1[[#This Row],[Details]:[Details]]=$B11)/(Table1[[#This Row],[Details]:[Details]]=$B11)*(ROW(Table1[[Details]:[Details]])-ROW(Table1[[#Headers],[Details]])),COLUMNS($C$10:CB10))),"")
A12: =COUNTIF(Table1[Details],B12) -> 2 | B12: =IFERROR(INDEX(Table1[Details],MATCH(0,INDEX(COUNTIF($B$10:B11,Table1[Details]),),0)),"") -> Adhesive | C12: =IF(COLUMNS($C$10:C11)<=$A12,INDEX(Table1[[PARTICULAR]:[PARTICULAR]],_xlfn.AGGREGATE(15,3,(Table1[[#This Row],[Details]:[Details]]=$B12)/(Table1[[#This Row],[Details]:[Details]]=$B12)*(ROW(Table1[[Details]:[Details]])-ROW(Table1[[#Headers],[Details]])),COLUMNS($C$10:C11))),"") -> Acrabond 20ml | D12: =IF(COLUMNS($C$10:D11)<=$A12,INDEX(Table1[[PARTICULAR]:[PARTICULAR]],_xlfn.AGGREGATE(15,3,(Table1[[#This Row],[Details]:[Details]]=$B12)/(Table1[[#This Row],[Details]:[Details]]=$B12)*(ROW(Table1[[Details]:[Details]])-ROW(Table1[[#Headers],[Details]])),COLUMNS($C$10:D11))),"") -> Adhesive Coated Tape | E12: =IF(COLUMNS($C$10:E11)<=$A12,INDEX(Table1[[PARTICULAR]:[PARTICULAR]],_xlfn.AGGREGATE(15,3,(Table1[[#This Row],[Details]:[Details]]=$B12)/(Table1[[#This Row],[Details]:[Details]]=$B12)*(ROW(Table1[[Details]:[Details]])-ROW(Table1[[#Headers],[Details]])),COLUMNS($C$10:E11))),"") | F12: =IF(COLUMNS($C$10:F11)<=$A12,INDEX(Table1[[PARTICULAR]:[PARTICULAR]],_xlfn.AGGREGATE(15,3,(Table1[[#This Row],[Details]:[Details]]=$B12)/(Table1[[#This Row],[Details]:[Details]]=$B12)*(ROW(Table1[[Details]:[Details]])-ROW(Table1[[#Headers],[Details]])),COLUMNS($C$10:F11))),"") | G12: =IF(COLUMNS($C$10:G11)<=$A12,INDEX(Table1[[PARTICULAR]:[PARTICULAR]],_xlfn.AGGREGATE(15,3,(Table1[[#This Row],[Details]:[Details]]=$B12)/(Table1[[#This Row],[Details]:[Details]]=$B12)*(ROW(Table1[[Details]:[Details]])-ROW(Table1[[#Headers],[Details]])),COLUMNS($C$10:G11))),"") | H12: =IF(COLUMNS($C$10:H11)<=$A12,INDEX(Table1[[PARTICULAR]:[PARTICULAR]],_xlfn.AGGREGATE(15,3,(Table1[[#This Row],[Details]:[Details]]=$B12)/(Table1[[#This Row],[Details]:[Details]]=$B12)*(ROW(Table1[[Details]:[Details]])-ROW(Table1[[#Headers],[Details]])),COLUMNS($C$10:H11))),"") | I12: =IF(COLUMNS($C$10:I11)<=$A12,INDEX(Table1[[PARTICULAR]:[PARTICULAR]],_xlfn.AGGREGATE(15,3,(Table1[[#This Row],[Details]:[Details]]=$B12)/(Table1[[#This Row],[Details]:[Details]]=$B12)*(ROW(Table1[[Details]:[Details]])-ROW(Table1[[#Headers],[Details]])),COLUMNS($C$10:I11))),"") | J12: =IF(COLUMNS($C$10:J11)<=$A12,INDEX(Table1[[PARTICULAR]:[PARTICULAR]],_xlfn.AGGREGATE(15,3,(Table1[[#This Row],[Details]:[Details]]=$B12)/(Table1[[#This Row],[Details]:[Details]]=$B12)*(ROW(Table1[[Details]:[Details]])-ROW(Table1[[#Headers],[Details]])),COLUMNS($C$10:J11))),"") | ... CB12: =IF(COLUMNS($C$10:CB11)<=$A12,INDEX(Table1[[PARTICULAR]:[PARTICULAR]],_xlfn.AGGREGATE(15,3,(Table1[[#This Row],[Details]:[Details]]=$B12)/(Table1[[#This Row],[Details]:[Details]]=$B12)*(ROW(Table1[[Details]:[Details]])-ROW(Table1[[#Headers],[Details]])),COLUMNS($C$10:CB11))),"")
A13: =COUNTIF(Table1[Details],B13) -> 2 | B13: =IFERROR(INDEX(Table1[Details],MATCH(0,INDEX(COUNTIF($B$10:B12,Table1[Details]),),0)),"") -> Canvas | C13: =IF(COLUMNS($C$10:C12)<=$A13,INDEX(Table1[[PARTICULAR]:[PARTICULAR]],_xlfn.AGGREGATE(15,3,(Table1[[#This Row],[Details]:[Details]]=$B13)/(Table1[[#This Row],[Details]:[Details]]=$B13)*(ROW(Table1[[Details]:[Details]])-ROW(Table1[[#Headers],[Details]])),COLUMNS($C$10:C12))),"") -> Eco Solvent Print On Canvas | D13: =IF(COLUMNS($C$10:D12)<=$A13,INDEX(Table1[[PARTICULAR]:[PARTICULAR]],_xlfn.AGGREGATE(15,3,(Table1[[#This Row],[Details]:[Details]]=$B13)/(Table1[[#This Row],[Details]:[Details]]=$B13)*(ROW(Table1[[Details]:[Details]])-ROW(Table1[[#Headers],[Details]])),COLUMNS($C$10:D12))),"") -> UV Print On Canvas | E13: =IF(COLUMNS($C$10:E12)<=$A13,INDEX(Table1[[PARTICULAR]:[PARTICULAR]],_xlfn.AGGREGATE(15,3,(Table1[[#This Row],[Details]:[Details]]=$B13)/(Table1[[#This Row],[Details]:[Details]]=$B13)*(ROW(Table1[[Details]:[Details]])-ROW(Table1[[#Headers],[Details]])),COLUMNS($C$10:E12))),"") | F13: =IF(COLUMNS($C$10:F12)<=$A13,INDEX(Table1[[PARTICULAR]:[PARTICULAR]],_xlfn.AGGREGATE(15,3,(Table1[[#This Row],[Details]:[Details]]=$B13)/(Table1[[#This Row],[Details]:[Details]]=$B13)*(ROW(Table1[[Details]:[Details]])-ROW(Table1[[#Headers],[Details]])),COLUMNS($C$10:F12))),"") | G13: =IF(COLUMNS($C$10:G12)<=$A13,INDEX(Table1[[PARTICULAR]:[PARTICULAR]],_xlfn.AGGREGATE(15,3,(Table1[[#This Row],[Details]:[Details]]=$B13)/(Table1[[#This Row],[Details]:[Details]]=$B13)*(ROW(Table1[[Details]:[Details]])-ROW(Table1[[#Headers],[Details]])),COLUMNS($C$10:G12))),"") | H13: =IF(COLUMNS($C$10:H12)<=$A13,INDEX(Table1[[PARTICULAR]:[PARTICULAR]],_xlfn.AGGREGATE(15,3,(Table1[[#This Row],[Details]:[Details]]=$B13)/(Table1[[#This Row],[Details]:[Details]]=$B13)*(ROW(Table1[[Details]:[Details]])-ROW(Table1[[#Headers],[Details]])),COLUMNS($C$10:H12))),"") | I13: =IF(COLUMNS($C$10:I12)<=$A13,INDEX(Table1[[PARTICULAR]:[PARTICULAR]],_xlfn.AGGREGATE(15,3,(Table1[[#This Row],[Details]:[Details]]=$B13)/(Table1[[#This Row],[Details]:[Details]]=$B13)*(ROW(Table1[[Details]:[Details]])-ROW(Table1[[#Headers],[Details]])),COLUMNS($C$10:I12))),"") | J13: =IF(COLUMNS($C$10:J12)<=$A13,INDEX(Table1[[PARTICULAR]:[PARTICULAR]],_xlfn.AGGREGATE(15,3,(Table1[[#This Row],[Details]:[Details]]=$B13)/(Table1[[#This Row],[Details]:[Details]]=$B13)*(ROW(Table1[[Details]:[Details]])-ROW(Table1[[#Headers],[Details]])),COLUMNS($C$10:J12))),"") | ... CB13: =IF(COLUMNS($C$10:CB12)<=$A13,INDEX(Table1[[PARTICULAR]:[PARTICULAR]],_xlfn.AGGREGATE(15,3,(Table1[[#This Row],[Details]:[Details]]=$B13)/(Table1[[#This Row],[Details]:[Details]]=$B13)*(ROW(Table1[[Details]:[Details]])-ROW(Table1[[#Headers],[Details]])),COLUMNS($C$10:CB12))),"")
A14: =COUNTIF(Table1[Details],B14) -> 19 | B14: =IFERROR(INDEX(Table1[Details],MATCH(0,INDEX(COUNTIF($B$10:B13,Table1[Details]),),0)),"") -> Latex | C14: =IF(COLUMNS($C$10:C13)<=$A14,INDEX(Table1[[PARTICULAR]:[PARTICULAR]],_xlfn.AGGREGATE(15,3,(Table1[[#This Row],[Details]:[Details]]=$B14)/(Table1[[#This Row],[Details]:[Details]]=$B14)*(ROW(Table1[[Details]:[Details]])-ROW(Table1[[#Headers],[Details]])),COLUMNS($C$10:C13))),"") -> Latex Print on Canvas | D14: =IF(COLUMNS($C$10:D13)<=$A14,INDEX(Table1[[PARTICULAR]:[PARTICULAR]],_xlfn.AGGREGATE(15,3,(Table1[[#This Row],[Details]:[Details]]=$B14)/(Table1[[#This Row],[Details]:[Details]]=$B14)*(ROW(Table1[[Details]:[Details]])-ROW(Table1[[#Headers],[Details]])),COLUMNS($C$10:D13))),"") -> 2 Side Latex Print on 3mm Sunboard | E14: =IF(COLUMNS($C$10:E13)<=$A14,INDEX(Table1[[PARTICULAR]:[PARTICULAR]],_xlfn.AGGREGATE(15,3,(Table1[[#This Row],[Details]:[Details]]=$B14)/(Table1[[#This Row],[Details]:[Details]]=$B14)*(ROW(Table1[[Details]:[Details]])-ROW(Table1[[#Headers],[Details]])),COLUMNS($C$10:E13))),"") -> 2 Side Latex Print on 5mm Sunboard | F14: =IF(COLUMNS($C$10:F13)<=$A14,INDEX(Table1[[PARTICULAR]:[PARTICULAR]],_xlfn.AGGREGATE(15,3,(Table1[[#This Row],[Details]:[Details]]=$B14)/(Table1[[#This Row],[Details]:[Details]]=$B14)*(ROW(Table1[[Details]:[Details]])-ROW(Table1[[#Headers],[Details]])),COLUMNS($C$10:F13))),"") -> LATEX Backlit Vinyl Print With Lam | G14: =IF(COLUMNS($C$10:G13)<=$A14,INDEX(Table1[[PARTICULAR]:[PARTICULAR]],_xlfn.AGGREGATE(15,3,(Table1[[#This Row],[Details]:[Details]]=$B14)/(Table1[[#This Row],[Details]:[Details]]=$B14)*(ROW(Table1[[Details]:[Details]])-ROW(Table1[[#Headers],[Details]])),COLUMNS($C$10:G13))),"") -> Latex Gray Back with Lamination | H14: =IF(COLUMNS($C$10:H13)<=$A14,INDEX(Table1[[PARTICULAR]:[PARTICULAR]],_xlfn.AGGREGATE(15,3,(Table1[[#This Row],[Details]:[Details]]=$B14)/(Table1[[#This Row],[Details]:[Details]]=$B14)*(ROW(Table1[[Details]:[Details]])-ROW(Table1[[#Headers],[Details]])),COLUMNS($C$10:H13))),"") -> Latex Gray Back with Lam+3mm SB | I14: =IF(COLUMNS($C$10:I13)<=$A14,INDEX(Table1[[PARTICULAR]:[PARTICULAR]],_xlfn.AGGREGATE(15,3,(Table1[[#This Row],[Details]:[Details]]=$B14)/(Table1[[#This Row],[Details]:[Details]]=$B14)*(ROW(Table1[[Details]:[Details]])-ROW(Table1[[#Headers],[Details]])),COLUMNS($C$10:I13))),"") -> Latex Gray Back with Lam+5mm SB | J14: =IF(COLUMNS($C$10:J13)<=$A14,INDEX(Table1[[PARTICULAR]:[PARTICULAR]],_xlfn.AGGREGATE(15,3,(Table1[[#This Row],[Details]:[Details]]=$B14)/(Table1[[#This Row],[Details]:[Details]]=$B14)*(ROW(Table1[[Details]:[Details]])-ROW(Table1[[#Headers],[Details]])),COLUMNS($C$10:J13))),"") -> Latex Translite Vinyl Print With Lam | ... CB14: =IF(COLUMNS($C$10:CB13)<=$A14,INDEX(Table1[[PARTICULAR]:[PARTICULAR]],_xlfn.AGGREGATE(15,3,(Table1[[#This Row],[Details]:[Details]]=$B14)/(Table1[[#This Row],[Details]:[Details]]=$B14)*(ROW(Table1[[Details]:[Details]])-ROW(Table1[[#Headers],[Details]])),COLUMNS($C$10:CB13))),"")
A15: =COUNTIF(Table1[Details],B15) -> 1 | B15: =IFERROR(INDEX(Table1[Details],MATCH(0,INDEX(COUNTIF($B$10:B14,Table1[Details]),),0)),"") -> Carpet | C15: =IF(COLUMNS($C$10:C14)<=$A15,INDEX(Table1[[PARTICULAR]:[PARTICULAR]],_xlfn.AGGREGATE(15,3,(Table1[[#This Row],[Details]:[Details]]=$B15)/(Table1[[#This Row],[Details]:[Details]]=$B15)*(ROW(Table1[[Details]:[Details]])-ROW(Table1[[#Headers],[Details]])),COLUMNS($C$10:C14))),"") -> Floor Carpet | D15: =IF(COLUMNS($C$10:D14)<=$A15,INDEX(Table1[[PARTICULAR]:[PARTICULAR]],_xlfn.AGGREGATE(15,3,(Table1[[#This Row],[Details]:[Details]]=$B15)/(Table1[[#This Row],[Details]:[Details]]=$B15)*(ROW(Table1[[Details]:[Details]])-ROW(Table1[[#Headers],[Details]])),COLUMNS($C$10:D14))),"") | E15: =IF(COLUMNS($C$10:E14)<=$A15,INDEX(Table1[[PARTICULAR]:[PARTICULAR]],_xlfn.AGGREGATE(15,3,(Table1[[#This Row],[Details]:[Details]]=$B15)/(Table1[[#This Row],[Details]:[Details]]=$B15)*(ROW(Table1[[Details]:[Details]])-ROW(Table1[[#Headers],[Details]])),COLUMNS($C$10:E14))),"") | F15: =IF(COLUMNS($C$10:F14)<=$A15,INDEX(Table1[[PARTICULAR]:[PARTICULAR]],_xlfn.AGGREGATE(15,3,(Table1[[#This Row],[Details]:[Details]]=$B15)/(Table1[[#This Row],[Details]:[Details]]=$B15)*(ROW(Table1[[Details]:[Details]])-ROW(Table1[[#Headers],[Details]])),COLUMNS($C$10:F14))),"") | G15: =IF(COLUMNS($C$10:G14)<=$A15,INDEX(Table1[[PARTICULAR]:[PARTICULAR]],_xlfn.AGGREGATE(15,3,(Table1[[#This Row],[Details]:[Details]]=$B15)/(Table1[[#This Row],[Details]:[Details]]=$B15)*(ROW(Table1[[Details]:[Details]])-ROW(Table1[[#Headers],[Details]])),COLUMNS($C$10:G14))),"") | H15: =IF(COLUMNS($C$10:H14)<=$A15,INDEX(Table1[[PARTICULAR]:[PARTICULAR]],_xlfn.AGGREGATE(15,3,(Table1[[#This Row],[Details]:[Details]]=$B15)/(Table1[[#This Row],[Details]:[Details]]=$B15)*(ROW(Table1[[Details]:[Details]])-ROW(Table1[[#Headers],[Details]])),COLUMNS($C$10:H14))),"") | I15: =IF(COLUMNS($C$10:I14)<=$A15,INDEX(Table1[[PARTICULAR]:[PARTICULAR]],_xlfn.AGGREGATE(15,3,(Table1[[#This Row],[Details]:[Details]]=$B15)/(Table1[[#This Row],[Details]:[Details]]=$B15)*(ROW(Table1[[Details]:[Details]])-ROW(Table1[[#Headers],[Details]])),COLUMNS($C$10:I14))),"") | J15: =IF(COLUMNS($C$10:J14)<=$A15,INDEX(Table1[[PARTICULAR]:[PARTICULAR]],_xlfn.AGGREGATE(15,3,(Table1[[#This Row],[Details]:[Details]]=$B15)/(Table1[[#This Row],[Details]:[Details]]=$B15)*(ROW(Table1[[Details]:[Details]])-ROW(Table1[[#Headers],[Details]])),COLUMNS($C$10:J14))),"") | ... CB15: =IF(COLUMNS($C$10:CB14)<=$A15,INDEX(Table1[[PARTICULAR]:[PARTICULAR]],_xlfn.AGGREGATE(15,3,(Table1[[#This Row],[Details]:[Details]]=$B15)/(Table1[[#This Row],[Details]:[Details]]=$B15)*(ROW(Table1[[Details]:[Details]])-ROW(Table1[[#Headers],[Details]])),COLUMNS($C$10:CB14))),"")
A16: =COUNTIF(Table1[Details],B16) -> 15 | B16: =IFERROR(INDEX(Table1[Details],MATCH(0,INDEX(COUNTIF($B$10:B15,Table1[Details]),),0)),"") -> Vinyl | C16: =IF(COLUMNS($C$10:C15)<=$A16,INDEX(Table1[[PARTICULAR]:[PARTICULAR]],_xlfn.AGGREGATE(15,3,(Table1[[#This Row],[Details]:[Details]]=$B16)/(Table1[[#This Row],[Details]:[Details]]=$B16)*(ROW(Table1[[Details]:[Details]])-ROW(Table1[[#Headers],[Details]])),COLUMNS($C$10:C15))),"") -> Clear Vinyl Printing | D16: =IF(COLUMNS($C$10:D15)<=$A16,INDEX(Table1[[PARTICULAR]:[PARTICULAR]],_xlfn.AGGREGATE(15,3,(Table1[[#This Row],[Details]:[Details]]=$B16)/(Table1[[#This Row],[Details]:[Details]]=$B16)*(ROW(Table1[[Details]:[Details]])-ROW(Table1[[#Headers],[Details]])),COLUMNS($C$10:D15))),"") -> Frosted Vinyl Cutting | E16: =IF(COLUMNS($C$10:E15)<=$A16,INDEX(Table1[[PARTICULAR]:[PARTICULAR]],_xlfn.AGGREGATE(15,3,(Table1[[#This Row],[Details]:[Details]]=$B16)/(Table1[[#This Row],[Details]:[Details]]=$B16)*(ROW(Table1[[Details]:[Details]])-ROW(Table1[[#Headers],[Details]])),COLUMNS($C$10:E15))),"") -> 3M Frosted Vinyl | F16: =IF(COLUMNS($C$10:F15)<=$A16,INDEX(Table1[[PARTICULAR]:[PARTICULAR]],_xlfn.AGGREGATE(15,3,(Table1[[#This Row],[Details]:[Details]]=$B16)/(Table1[[#This Row],[Details]:[Details]]=$B16)*(ROW(Table1[[Details]:[Details]])-ROW(Table1[[#Headers],[Details]])),COLUMNS($C$10:F15))),"") -> Lamination | G16: =IF(COLUMNS($C$10:G15)<=$A16,INDEX(Table1[[PARTICULAR]:[PARTICULAR]],_xlfn.AGGREGATE(15,3,(Table1[[#This Row],[Details]:[Details]]=$B16)/(Table1[[#This Row],[Details]:[Details]]=$B16)*(ROW(Table1[[Details]:[Details]])-ROW(Table1[[#Headers],[Details]])),COLUMNS($C$10:G15))),"") -> BLACK VINYL | H16: =IF(COLUMNS($C$10:H15)<=$A16,INDEX(Table1[[PARTICULAR]:[PARTICULAR]],_xlfn.AGGREGATE(15,3,(Table1[[#This Row],[Details]:[Details]]=$B16)/(Table1[[#This Row],[Details]:[Details]]=$B16)*(ROW(Table1[[Details]:[Details]])-ROW(Table1[[#Headers],[Details]])),COLUMNS($C$10:H15))),"") -> GOLDEN BRUSH VINYL | I16: =IF(COLUMNS($C$10:I15)<=$A16,INDEX(Table1[[PARTICULAR]:[PARTICULAR]],_xlfn.AGGREGATE(15,3,(Table1[[#This Row],[Details]:[Details]]=$B16)/(Table1[[#This Row],[Details]:[Details]]=$B16)*(ROW(Table1[[Details]:[Details]])-ROW(Table1[[#Headers],[Details]])),COLUMNS($C$10:I15))),"") -> Grey Back Vinyl | J16: =IF(COLUMNS($C$10:J15)<=$A16,INDEX(Table1[[PARTICULAR]:[PARTICULAR]],_xlfn.AGGREGATE(15,3,(Table1[[#This Row],[Details]:[Details]]=$B16)/(Table1[[#This Row],[Details]:[Details]]=$B16)*(ROW(Table1[[Details]:[Details]])-ROW(Table1[[#Headers],[Details]])),COLUMNS($C$10:J15))),"") -> Plain Frosted Vinyl | ... CB16: =IF(COLUMNS($C$10:CB15)<=$A16,INDEX(Table1[[PARTICULAR]:[PARTICULAR]],_xlfn.AGGREGATE(15,3,(Table1[[#This Row],[Details]:[Details]]=$B16)/(Table1[[#This Row],[Details]:[Details]]=$B16)*(ROW(Table1[[Details]:[Details]])-ROW(Table1[[#Headers],[Details]])),COLUMNS($C$10:CB15))),"")
A17: =COUNTIF(Table1[Details],B17) -> 3 | B17: =IFERROR(INDEX(Table1[Details],MATCH(0,INDEX(COUNTIF($B$10:B16,Table1[Details]),),0)),"") -> Fabric | C17: =IF(COLUMNS($C$10:C16)<=$A17,INDEX(Table1[[PARTICULAR]:[PARTICULAR]],_xlfn.AGGREGATE(15,3,(Table1[[#This Row],[Details]:[Details]]=$B17)/(Table1[[#This Row],[Details]:[Details]]=$B17)*(ROW(Table1[[Details]:[Details]])-ROW(Table1[[#Headers],[Details]])),COLUMNS($C$10:C16))),"") -> FABRIC PRINT WITH SILICON TAPE & STITCHI | D17: =IF(COLUMNS($C$10:D16)<=$A17,INDEX(Table1[[PARTICULAR]:[PARTICULAR]],_xlfn.AGGREGATE(15,3,(Table1[[#This Row],[Details]:[Details]]=$B17)/(Table1[[#This Row],[Details]:[Details]]=$B17)*(ROW(Table1[[Details]:[Details]])-ROW(Table1[[#Headers],[Details]])),COLUMNS($C$10:D16))),"") -> Organza Fabric white Color | E17: =IF(COLUMNS($C$10:E16)<=$A17,INDEX(Table1[[PARTICULAR]:[PARTICULAR]],_xlfn.AGGREGATE(15,3,(Table1[[#This Row],[Details]:[Details]]=$B17)/(Table1[[#This Row],[Details]:[Details]]=$B17)*(ROW(Table1[[Details]:[Details]])-ROW(Table1[[#Headers],[Details]])),COLUMNS($C$10:E16))),"") -> UV PRINTED POLYESTER BACKLIT FABRIC | F17: =IF(COLUMNS($C$10:F16)<=$A17,INDEX(Table1[[PARTICULAR]:[PARTICULAR]],_xlfn.AGGREGATE(15,3,(Table1[[#This Row],[Details]:[Details]]=$B17)/(Table1[[#This Row],[Details]:[Details]]=$B17)*(ROW(Table1[[Details]:[Details]])-ROW(Table1[[#Headers],[Details]])),COLUMNS($C$10:F16))),"") | G17: =IF(COLUMNS($C$10:G16)<=$A17,INDEX(Table1[[PARTICULAR]:[PARTICULAR]],_xlfn.AGGREGATE(15,3,(Table1[[#This Row],[Details]:[Details]]=$B17)/(Table1[[#This Row],[Details]:[Details]]=$B17)*(ROW(Table1[[Details]:[Details]])-ROW(Table1[[#Headers],[Details]])),COLUMNS($C$10:G16))),"") | H17: =IF(COLUMNS($C$10:H16)<=$A17,INDEX(Table1[[PARTICULAR]:[PARTICULAR]],_xlfn.AGGREGATE(15,3,(Table1[[#This Row],[Details]:[Details]]=$B17)/(Table1[[#This Row],[Details]:[Details]]=$B17)*(ROW(Table1[[Details]:[Details]])-ROW(Table1[[#Headers],[Details]])),COLUMNS($C$10:H16))),"") | I17: =IF(COLUMNS($C$10:I16)<=$A17,INDEX(Table1[[PARTICULAR]:[PARTICULAR]],_xlfn.AGGREGATE(15,3,(Table1[[#This Row],[Details]:[Details]]=$B17)/(Table1[[#This Row],[Details]:[Details]]=$B17)*(ROW(Table1[[Details]:[Details]])-ROW(Table1[[#Headers],[Details]])),COLUMNS($C$10:I16))),"") | J17: =IF(COLUMNS($C$10:J16)<=$A17,INDEX(Table1[[PARTICULAR]:[PARTICULAR]],_xlfn.AGGREGATE(15,3,(Table1[[#This Row],[Details]:[Details]]=$B17)/(Table1[[#This Row],[Details]:[Details]]=$B17)*(ROW(Table1[[Details]:[Details]])-ROW(Table1[[#Headers],[Details]])),COLUMNS($C$10:J16))),"") | ... CB17: =IF(COLUMNS($C$10:CB16)<=$A17,INDEX(Table1[[PARTICULAR]:[PARTICULAR]],_xlfn.AGGREGATE(15,3,(Table1[[#This Row],[Details]:[Details]]=$B17)/(Table1[[#This Row],[Details]:[Details]]=$B17)*(ROW(Table1[[Details]:[Details]])-ROW(Table1[[#Headers],[Details]])),COLUMNS($C$10:CB16))),"")
A18: =COUNTIF(Table1[Details],B18) -> 9 | B18: =IFERROR(INDEX(Table1[Details],MATCH(0,INDEX(COUNTIF($B$10:B17,Table1[Details]),),0)),"") -> Flex | C18: =IF(COLUMNS($C$10:C17)<=$A18,INDEX(Table1[[PARTICULAR]:[PARTICULAR]],_xlfn.AGGREGATE(15,3,(Table1[[#This Row],[Details]:[Details]]=$B18)/(Table1[[#This Row],[Details]:[Details]]=$B18)*(ROW(Table1[[Details]:[Details]])-ROW(Table1[[#Headers],[Details]])),COLUMNS($C$10:C17))),"") -> Star Flex Eco solvent Print | D18: =IF(COLUMNS($C$10:D17)<=$A18,INDEX(Table1[[PARTICULAR]:[PARTICULAR]],_xlfn.AGGREGATE(15,3,(Table1[[#This Row],[Details]:[Details]]=$B18)/(Table1[[#This Row],[Details]:[Details]]=$B18)*(ROW(Table1[[Details]:[Details]])-ROW(Table1[[#Headers],[Details]])),COLUMNS($C$10:D17))),"") -> Plain Flex | E18: =IF(COLUMNS($C$10:E17)<=$A18,INDEX(Table1[[PARTICULAR]:[PARTICULAR]],_xlfn.AGGREGATE(15,3,(Table1[[#This Row],[Details]:[Details]]=$B18)/(Table1[[#This Row],[Details]:[Details]]=$B18)*(ROW(Table1[[Details]:[Details]])-ROW(Table1[[#Headers],[Details]])),COLUMNS($C$10:E17))),"") -> Backlit Flex Printing | F18: =IF(COLUMNS($C$10:F17)<=$A18,INDEX(Table1[[PARTICULAR]:[PARTICULAR]],_xlfn.AGGREGATE(15,3,(Table1[[#This Row],[Details]:[Details]]=$B18)/(Table1[[#This Row],[Details]:[Details]]=$B18)*(ROW(Table1[[Details]:[Details]])-ROW(Table1[[#Headers],[Details]])),COLUMNS($C$10:F17))),"") -> BACKLIT FLEX PRINT-16 OZ | G18: =IF(COLUMNS($C$10:G17)<=$A18,INDEX(Table1[[PARTICULAR]:[PARTICULAR]],_xlfn.AGGREGATE(15,3,(Table1[[#This Row],[Details]:[Details]]=$B18)/(Table1[[#This Row],[Details]:[Details]]=$B18)*(ROW(Table1[[Details]:[Details]])-ROW(Table1[[#Headers],[Details]])),COLUMNS($C$10:G17))),"") -> Frontlit Flex Printing | H18: =IF(COLUMNS($C$10:H17)<=$A18,INDEX(Table1[[PARTICULAR]:[PARTICULAR]],_xlfn.AGGREGATE(15,3,(Table1[[#This Row],[Details]:[Details]]=$B18)/(Table1[[#This Row],[Details]:[Details]]=$B18)*(ROW(Table1[[Details]:[Details]])-ROW(Table1[[#Headers],[Details]])),COLUMNS($C$10:H17))),"") -> Frontlit Flex Print On Branded Media | I18: =IF(COLUMNS($C$10:I17)<=$A18,INDEX(Table1[[PARTICULAR]:[PARTICULAR]],_xlfn.AGGREGATE(15,3,(Table1[[#This Row],[Details]:[Details]]=$B18)/(Table1[[#This Row],[Details]:[Details]]=$B18)*(ROW(Table1[[Details]:[Details]])-ROW(Table1[[#Headers],[Details]])),COLUMNS($C$10:I17))),"") -> PVC Flex | J18: =IF(COLUMNS($C$10:J17)<=$A18,INDEX(Table1[[PARTICULAR]:[PARTICULAR]],_xlfn.AGGREGATE(15,3,(Table1[[#This Row],[Details]:[Details]]=$B18)/(Table1[[#This Row],[Details]:[Details]]=$B18)*(ROW(Table1[[Details]:[Details]])-ROW(Table1[[#Headers],[Details]])),COLUMNS($C$10:J17))),"") -> Flex Mounting & Fitting Charges | ... CB18: =IF(COLUMNS($C$10:CB17)<=$A18,INDEX(Table1[[PARTICULAR]:[PARTICULAR]],_xlfn.AGGREGATE(15,3,(Table1[[#This Row],[Details]:[Details]]=$B18)/(Table1[[#This Row],[Details]:[Details]]=$B18)*(ROW(Table1[[Details]:[Details]])-ROW(Table1[[#Headers],[Details]])),COLUMNS($C$10:CB17))),"")
A19: =COUNTIF(Table1[Details],B19) -> 33 | B19: =IFERROR(INDEX(Table1[Details],MATCH(0,INDEX(COUNTIF($B$10:B18,Table1[Details]),),0)),"") -> Light/Festive | C19: =IF(COLUMNS($C$10:C18)<=$A19,INDEX(Table1[[PARTICULAR]:[PARTICULAR]],_xlfn.AGGREGATE(15,3,(Table1[[#This Row],[Details]:[Details]]=$B19)/(Table1[[#This Row],[Details]:[Details]]=$B19)*(ROW(Table1[[Details]:[Details]])-ROW(Table1[[#Headers],[Details]])),COLUMNS($C$10:C18))),"") -> TUBELIGHT,CHOWK & WIRING | D19: =IF(COLUMNS($C$10:D18)<=$A19,INDEX(Table1[[PARTICULAR]:[PARTICULAR]],_xlfn.AGGREGATE(15,3,(Table1[[#This Row],[Details]:[Details]]=$B19)/(Table1[[#This Row],[Details]:[Details]]=$B19)*(ROW(Table1[[Details]:[Details]])-ROW(Table1[[#Headers],[Details]])),COLUMNS($C$10:D18))),"") -> 1.2mm Rope Wire | E19: =IF(COLUMNS($C$10:E18)<=$A19,INDEX(Table1[[PARTICULAR]:[PARTICULAR]],_xlfn.AGGREGATE(15,3,(Table1[[#This Row],[Details]:[Details]]=$B19)/(Table1[[#This Row],[Details]:[Details]]=$B19)*(ROW(Table1[[Details]:[Details]])-ROW(Table1[[#Headers],[Details]])),COLUMNS($C$10:E18))),"") -> 250W LED Drivers | F19: =IF(COLUMNS($C$10:F18)<=$A19,INDEX(Table1[[PARTICULAR]:[PARTICULAR]],_xlfn.AGGREGATE(15,3,(Table1[[#This Row],[Details]:[Details]]=$B19)/(Table1[[#This Row],[Details]:[Details]]=$B19)*(ROW(Table1[[Details]:[Details]])-ROW(Table1[[#Headers],[Details]])),COLUMNS($C$10:F18))),"") -> Aluminium Profile Fabric LIT Box | G19: =IF(COLUMNS($C$10:G18)<=$A19,INDEX(Table1[[PARTICULAR]:[PARTICULAR]],_xlfn.AGGREGATE(15,3,(Table1[[#This Row],[Details]:[Details]]=$B19)/(Table1[[#This Row],[Details]:[Details]]=$B19)*(ROW(Table1[[Details]:[Details]])-ROW(Table1[[#Headers],[Details]])),COLUMNS($C$10:G18))),"") -> Arch Gate MS HB | H19: =IF(COLUMNS($C$10:H18)<=$A19,INDEX(Table1[[PARTICULAR]:[PARTICULAR]],_xlfn.AGGREGATE(15,3,(Table1[[#This Row],[Details]:[Details]]=$B19)/(Table1[[#This Row],[Details]:[Details]]=$B19)*(ROW(Table1[[Details]:[Details]])-ROW(Table1[[#Headers],[Details]])),COLUMNS($C$10:H18))),"") -> Arch Gate MS LB | I19: =IF(COLUMNS($C$10:I18)<=$A19,INDEX(Table1[[PARTICULAR]:[PARTICULAR]],_xlfn.AGGREGATE(15,3,(Table1[[#This Row],[Details]:[Details]]=$B19)/(Table1[[#This Row],[Details]:[Details]]=$B19)*(ROW(Table1[[Details]:[Details]])-ROW(Table1[[#Headers],[Details]])),COLUMNS($C$10:I18))),"") -> Arch Gate MS MB | J19: =IF(COLUMNS($C$10:J18)<=$A19,INDEX(Table1[[PARTICULAR]:[PARTICULAR]],_xlfn.AGGREGATE(15,3,(Table1[[#This Row],[Details]:[Details]]=$B19)/(Table1[[#This Row],[Details]:[Details]]=$B19)*(ROW(Table1[[Details]:[Details]])-ROW(Table1[[#Headers],[Details]])),COLUMNS($C$10:J18))),"") -> Dangler 3F | ... CB19: =IF(COLUMNS($C$10:CB18)<=$A19,INDEX(Table1[[PARTICULAR]:[PARTICULAR]],_xlfn.AGGREGATE(15,3,(Table1[[#This Row],[Details]:[Details]]=$B19)/(Table1[[#This Row],[Details]:[Details]]=$B19)*(ROW(Table1[[Details]:[Details]])-ROW(Table1[[#Headers],[Details]])),COLUMNS($C$10:CB18))),"")
A20: =COUNTIF(Table1[Details],B20) -> 8 | B20: =IFERROR(INDEX(Table1[Details],MATCH(0,INDEX(COUNTIF($B$10:B19,Table1[Details]),),0)),"") -> Metal | C20: =IF(COLUMNS($C$10:C19)<=$A20,INDEX(Table1[[PARTICULAR]:[PARTICULAR]],_xlfn.AGGREGATE(15,3,(Table1[[#This Row],[Details]:[Details]]=$B20)/(Table1[[#This Row],[Details]:[Details]]=$B20)*(ROW(Table1[[Details]:[Details]])-ROW(Table1[[#Headers],[Details]])),COLUMNS($C$10:C19))),"") -> J Hook | D20: =IF(COLUMNS($C$10:D19)<=$A20,INDEX(Table1[[PARTICULAR]:[PARTICULAR]],_xlfn.AGGREGATE(15,3,(Table1[[#This Row],[Details]:[Details]]=$B20)/(Table1[[#This Row],[Details]:[Details]]=$B20)*(ROW(Table1[[Details]:[Details]])-ROW(Table1[[#Headers],[Details]])),COLUMNS($C$10:D19))),"") -> S Hook | E20: =IF(COLUMNS($C$10:E19)<=$A20,INDEX(Table1[[PARTICULAR]:[PARTICULAR]],_xlfn.AGGREGATE(15,3,(Table1[[#This Row],[Details]:[Details]]=$B20)/(Table1[[#This Row],[Details]:[Details]]=$B20)*(ROW(Table1[[Details]:[Details]])-ROW(Table1[[#Headers],[Details]])),COLUMNS($C$10:E19))),"") -> MODULAR FIXTURE 4FT X 7FT | F20: =IF(COLUMNS($C$10:F19)<=$A20,INDEX(Table1[[PARTICULAR]:[PARTICULAR]],_xlfn.AGGREGATE(15,3,(Table1[[#This Row],[Details]:[Details]]=$B20)/(Table1[[#This Row],[Details]:[Details]]=$B20)*(ROW(Table1[[Details]:[Details]])-ROW(Table1[[#Headers],[Details]])),COLUMNS($C$10:F19))),"") -> MODULAR FIXTURE 4FT X 8FT | G20: =IF(COLUMNS($C$10:G19)<=$A20,INDEX(Table1[[PARTICULAR]:[PARTICULAR]],_xlfn.AGGREGATE(15,3,(Table1[[#This Row],[Details]:[Details]]=$B20)/(Table1[[#This Row],[Details]:[Details]]=$B20)*(ROW(Table1[[Details]:[Details]])-ROW(Table1[[#Headers],[Details]])),COLUMNS($C$10:G19))),"") -> MS Frame Standee Structure | H20: =IF(COLUMNS($C$10:H19)<=$A20,INDEX(Table1[[PARTICULAR]:[PARTICULAR]],_xlfn.AGGREGATE(15,3,(Table1[[#This Row],[Details]:[Details]]=$B20)/(Table1[[#This Row],[Details]:[Details]]=$B20)*(ROW(Table1[[Details]:[Details]])-ROW(Table1[[#Headers],[Details]])),COLUMNS($C$10:H19))),"") -> MS Frame Standee(Wrought Iron) | I20: =IF(COLUMNS($C$10:I19)<=$A20,INDEX(Table1[[PARTICULAR]:[PARTICULAR]],_xlfn.AGGREGATE(15,3,(Table1[[#This Row],[Details]:[Details]]=$B20)/(Table1[[#This Row],[Details]:[Details]]=$B20)*(ROW(Table1[[Details]:[Details]])-ROW(Table1[[#Headers],[Details]])),COLUMNS($C$10:I19))),"") -> MS Frame Structure | J20: =IF(COLUMNS($C$10:J19)<=$A20,INDEX(Table1[[PARTICULAR]:[PARTICULAR]],_xlfn.AGGREGATE(15,3,(Table1[[#This Row],[Details]:[Details]]=$B20)/(Table1[[#This Row],[Details]:[Details]]=$B20)*(ROW(Table1[[Details]:[Details]])-ROW(Table1[[#Headers],[Details]])),COLUMNS($C$10:J19))),"") -> Store Directory | ... CB20: =IF(COLUMNS($C$10:CB19)<=$A20,INDEX(Table1[[PARTICULAR]:[PARTICULAR]],_xlfn.AGGREGATE(15,3,(Table1[[#This Row],[Details]:[Details]]=$B20)/(Table1[[#This Row],[Details]:[Details]]=$B20)*(ROW(Table1[[Details]:[Details]])-ROW(Table1[[#Headers],[Details]])),COLUMNS($C$10:CB19))),"")
A21: =COUNTIF(Table1[Details],B21) -> 9 | B21: =IFERROR(INDEX(Table1[Details],MATCH(0,INDEX(COUNTIF($B$10:B20,Table1[Details]),),0)),"") -> Digital | C21: =IF(COLUMNS($C$10:C20)<=$A21,INDEX(Table1[[PARTICULAR]:[PARTICULAR]],_xlfn.AGGREGATE(15,3,(Table1[[#This Row],[Details]:[Details]]=$B21)/(Table1[[#This Row],[Details]:[Details]]=$B21)*(ROW(Table1[[Details]:[Details]])-ROW(Table1[[#Headers],[Details]])),COLUMNS($C$10:C20))),"") -> A3 - Danglers - Digital | D21: =IF(COLUMNS($C$10:D20)<=$A21,INDEX(Table1[[PARTICULAR]:[PARTICULAR]],_xlfn.AGGREGATE(15,3,(Table1[[#This Row],[Details]:[Details]]=$B21)/(Table1[[#This Row],[Details]:[Details]]=$B21)*(ROW(Table1[[Details]:[Details]])-ROW(Table1[[#Headers],[Details]])),COLUMNS($C$10:D20))),"") -> A3 - Signage - Digital | E21: =IF(COLUMNS($C$10:E20)<=$A21,INDEX(Table1[[PARTICULAR]:[PARTICULAR]],_xlfn.AGGREGATE(15,3,(Table1[[#This Row],[Details]:[Details]]=$B21)/(Table1[[#This Row],[Details]:[Details]]=$B21)*(ROW(Table1[[Details]:[Details]])-ROW(Table1[[#Headers],[Details]])),COLUMNS($C$10:E20))),"") -> A4 - Signage - Digital | F21: =IF(COLUMNS($C$10:F20)<=$A21,INDEX(Table1[[PARTICULAR]:[PARTICULAR]],_xlfn.AGGREGATE(15,3,(Table1[[#This Row],[Details]:[Details]]=$B21)/(Table1[[#This Row],[Details]:[Details]]=$B21)*(ROW(Table1[[Details]:[Details]])-ROW(Table1[[#Headers],[Details]])),COLUMNS($C$10:F20))),"") -> A5 - Signage - Digital | G21: =IF(COLUMNS($C$10:G20)<=$A21,INDEX(Table1[[PARTICULAR]:[PARTICULAR]],_xlfn.AGGREGATE(15,3,(Table1[[#This Row],[Details]:[Details]]=$B21)/(Table1[[#This Row],[Details]:[Details]]=$B21)*(ROW(Table1[[Details]:[Details]])-ROW(Table1[[#Headers],[Details]])),COLUMNS($C$10:G20))),"") -> Shelf Talker 6" X 8" - Digital | H21: =IF(COLUMNS($C$10:H20)<=$A21,INDEX(Table1[[PARTICULAR]:[PARTICULAR]],_xlfn.AGGREGATE(15,3,(Table1[[#This Row],[Details]:[Details]]=$B21)/(Table1[[#This Row],[Details]:[Details]]=$B21)*(ROW(Table1[[Details]:[Details]])-ROW(Table1[[#Headers],[Details]])),COLUMNS($C$10:H20))),"") -> Wobbler Printing - Digital | I21: =IF(COLUMNS($C$10:I20)<=$A21,INDEX(Table1[[PARTICULAR]:[PARTICULAR]],_xlfn.AGGREGATE(15,3,(Table1[[#This Row],[Details]:[Details]]=$B21)/(Table1[[#This Row],[Details]:[Details]]=$B21)*(ROW(Table1[[Details]:[Details]])-ROW(Table1[[#Headers],[Details]])),COLUMNS($C$10:I20))),"") -> A2 - SIGNAGE - DIGITAL 300GSM | J21: =IF(COLUMNS($C$10:J20)<=$A21,INDEX(Table1[[PARTICULAR]:[PARTICULAR]],_xlfn.AGGREGATE(15,3,(Table1[[#This Row],[Details]:[Details]]=$B21)/(Table1[[#This Row],[Details]:[Details]]=$B21)*(ROW(Table1[[Details]:[Details]])-ROW(Table1[[#Headers],[Details]])),COLUMNS($C$10:J20))),"") -> A3 Sticker Paper | ... CB21: =IF(COLUMNS($C$10:CB20)<=$A21,INDEX(Table1[[PARTICULAR]:[PARTICULAR]],_xlfn.AGGREGATE(15,3,(Table1[[#This Row],[Details]:[Details]]=$B21)/(Table1[[#This Row],[Details]:[Details]]=$B21)*(ROW(Table1[[Details]:[Details]])-ROW(Table1[[#Headers],[Details]])),COLUMNS($C$10:CB20))),"")
A22: =COUNTIF(Table1[Details],B22) -> 14 | B22: =IFERROR(INDEX(Table1[Details],MATCH(0,INDEX(COUNTIF($B$10:B21,Table1[Details]),),0)),"") -> Offset | C22: =IF(COLUMNS($C$10:C21)<=$A22,INDEX(Table1[[PARTICULAR]:[PARTICULAR]],_xlfn.AGGREGATE(15,3,(Table1[[#This Row],[Details]:[Details]]=$B22)/(Table1[[#This Row],[Details]:[Details]]=$B22)*(ROW(Table1[[Details]:[Details]])-ROW(Table1[[#Headers],[Details]])),COLUMNS($C$10:C21))),"") -> A3 - Danglers - Offset | D22: =IF(COLUMNS($C$10:D21)<=$A22,INDEX(Table1[[PARTICULAR]:[PARTICULAR]],_xlfn.AGGREGATE(15,3,(Table1[[#This Row],[Details]:[Details]]=$B22)/(Table1[[#This Row],[Details]:[Details]]=$B22)*(ROW(Table1[[Details]:[Details]])-ROW(Table1[[#Headers],[Details]])),COLUMNS($C$10:D21))),"") -> A4 - Signage - Offset | E22: =IF(COLUMNS($C$10:E21)<=$A22,INDEX(Table1[[PARTICULAR]:[PARTICULAR]],_xlfn.AGGREGATE(15,3,(Table1[[#This Row],[Details]:[Details]]=$B22)/(Table1[[#This Row],[Details]:[Details]]=$B22)*(ROW(Table1[[Details]:[Details]])-ROW(Table1[[#Headers],[Details]])),COLUMNS($C$10:E21))),"") -> A5 - Signage - Offset | F22: =IF(COLUMNS($C$10:F21)<=$A22,INDEX(Table1[[PARTICULAR]:[PARTICULAR]],_xlfn.AGGREGATE(15,3,(Table1[[#This Row],[Details]:[Details]]=$B22)/(Table1[[#This Row],[Details]:[Details]]=$B22)*(ROW(Table1[[Details]:[Details]])-ROW(Table1[[#Headers],[Details]])),COLUMNS($C$10:F21))),"") -> Shelf Talker 2" X 5.5" - Offset | G22: =IF(COLUMNS($C$10:G21)<=$A22,INDEX(Table1[[PARTICULAR]:[PARTICULAR]],_xlfn.AGGREGATE(15,3,(Table1[[#This Row],[Details]:[Details]]=$B22)/(Table1[[#This Row],[Details]:[Details]]=$B22)*(ROW(Table1[[Details]:[Details]])-ROW(Table1[[#Headers],[Details]])),COLUMNS($C$10:G21))),"") -> Shelf Talker 6" X 8" - Offset | H22: =IF(COLUMNS($C$10:H21)<=$A22,INDEX(Table1[[PARTICULAR]:[PARTICULAR]],_xlfn.AGGREGATE(15,3,(Table1[[#This Row],[Details]:[Details]]=$B22)/(Table1[[#This Row],[Details]:[Details]]=$B22)*(ROW(Table1[[Details]:[Details]])-ROW(Table1[[#Headers],[Details]])),COLUMNS($C$10:H21))),"") -> Blank Signage Paper - A4 | I22: =IF(COLUMNS($C$10:I21)<=$A22,INDEX(Table1[[PARTICULAR]:[PARTICULAR]],_xlfn.AGGREGATE(15,3,(Table1[[#This Row],[Details]:[Details]]=$B22)/(Table1[[#This Row],[Details]:[Details]]=$B22)*(ROW(Table1[[Details]:[Details]])-ROW(Table1[[#Headers],[Details]])),COLUMNS($C$10:I21))),"") -> Blank Signage Paper - A5 | J22: =IF(COLUMNS($C$10:J21)<=$A22,INDEX(Table1[[PARTICULAR]:[PARTICULAR]],_xlfn.AGGREGATE(15,3,(Table1[[#This Row],[Details]:[Details]]=$B22)/(Table1[[#This Row],[Details]:[Details]]=$B22)*(ROW(Table1[[Details]:[Details]])-ROW(Table1[[#Headers],[Details]])),COLUMNS($C$10:J21))),"") -> A3 Generic Signage Offset | ... CB22: =IF(COLUMNS($C$10:CB21)<=$A22,INDEX(Table1[[PARTICULAR]:[PARTICULAR]],_xlfn.AGGREGATE(15,3,(Table1[[#This Row],[Details]:[Details]]=$B22)/(Table1[[#This Row],[Details]:[Details]]=$B22)*(ROW(Table1[[Details]:[Details]])-ROW(Table1[[#Headers],[Details]])),COLUMNS($C$10:CB21))),"")
... A34: =COUNTIF(Table1[Details],B34) -> 1 | B34: =IFERROR(INDEX(Table1[Details],MATCH(0,INDEX(COUNTIF($B$10:B33,Table1[Details]),),0)),"") -> T shirt | C34: =IF(COLUMNS($C$10:C33)<=$A34,INDEX(Table1[[PARTICULAR]:[PARTICULAR]],_xlfn.AGGREGATE(15,3,(Table1[[#This Row],[Details]:[Details]]=$B34)/(Table1[[#This Row],[Details]:[Details]]=$B34)*(ROW(Table1[[Details]:[Details]])-ROW(Table1[[#Headers],[Details]])),COLUMNS($C$10:C33))),"") -> T SHIRT | D34: =IF(COLUMNS($C$10:D33)<=$A34,INDEX(Table1[[PARTICULAR]:[PARTICULAR]],_xlfn.AGGREGATE(15,3,(Table1[[#This Row],[Details]:[Details]]=$B34)/(Table1[[#This Row],[Details]:[Details]]=$B34)*(ROW(Table1[[Details]:[Details]])-ROW(Table1[[#Headers],[Details]])),COLUMNS($C$10:D33))),"") | E34: =IF(COLUMNS($C$10:E33)<=$A34,INDEX(Table1[[PARTICULAR]:[PARTICULAR]],_xlfn.AGGREGATE(15,3,(Table1[[#This Row],[Details]:[Details]]=$B34)/(Table1[[#This Row],[Details]:[Details]]=$B34)*(ROW(Table1[[Details]:[Details]])-ROW(Table1[[#Headers],[Details]])),COLUMNS($C$10:E33))),"") | F34: =IF(COLUMNS($C$10:F33)<=$A34,INDEX(Table1[[PARTICULAR]:[PARTICULAR]],_xlfn.AGGREGATE(15,3,(Table1[[#This Row],[Details]:[Details]]=$B34)/(Table1[[#This Row],[Details]:[Details]]=$B34)*(ROW(Table1[[Details]:[Details]])-ROW(Table1[[#Headers],[Details]])),COLUMNS($C$10:F33))),"") | G34: =IF(COLUMNS($C$10:G33)<=$A34,INDEX(Table1[[PARTICULAR]:[PARTICULAR]],_xlfn.AGGREGATE(15,3,(Table1[[#This Row],[Details]:[Details]]=$B34)/(Table1[[#This Row],[Details]:[Details]]=$B34)*(ROW(Table1[[Details]:[Details]])-ROW(Table1[[#Headers],[Details]])),COLUMNS($C$10:G33))),"") | H34: =IF(COLUMNS($C$10:H33)<=$A34,INDEX(Table1[[PARTICULAR]:[PARTICULAR]],_xlfn.AGGREGATE(15,3,(Table1[[#This Row],[Details]:[Details]]=$B34)/(Table1[[#This Row],[Details]:[Details]]=$B34)*(ROW(Table1[[Details]:[Details]])-ROW(Table1[[#Headers],[Details]])),COLUMNS($C$10:H33))),"") | I34: =IF(COLUMNS($C$10:I33)<=$A34,INDEX(Table1[[PARTICULAR]:[PARTICULAR]],_xlfn.AGGREGATE(15,3,(Table1[[#This Row],[Details]:[Details]]=$B34)/(Table1[[#This Row],[Details]:[Details]]=$B34)*(ROW(Table1[[Details]:[Details]])-ROW(Table1[[#Headers],[Details]])),COLUMNS($C$10:I33))),"") | J34: =IF(COLUMNS($C$10:J33)<=$A34,INDEX(Table1[[PARTICULAR]:[PARTICULAR]],_xlfn.AGGREGATE(15,3,(Table1[[#This Row],[Details]:[Details]]=$B34)/(Table1[[#This Row],[Details]:[Details]]=$B34)*(ROW(Table1[[Details]:[Details]])-ROW(Table1[[#Headers],[Details]])),COLUMNS($C$10:J33))),"") | ... CB34: =IF(COLUMNS($C$10:CB33)<=$A34,INDEX(Table1[[PARTICULAR]:[PARTICULAR]],_xlfn.AGGREGATE(15,3,(Table1[[#This Row],[Details]:[Details]]=$B34)/(Table1[[#This Row],[Details]:[Details]]=$B34)*(ROW(Table1[[Details]:[Details]])-ROW(Table1[[#Headers],[Details]])),COLUMNS($C$10:CB33))),"")
B35: =IFERROR(INDEX(Table1[Details],MATCH(0,INDEX(COUNTIF($B$10:B34,Table1[Details]),),0)),"") -> 0 | C35: =IF(COLUMNS($C$10:C34)<=$A35,INDEX(Table1[[PARTICULAR]:[PARTICULAR]],_xlfn.AGGREGATE(15,3,(Table1[[#This Row],[Details]:[Details]]=$B35)/(Table1[[#This Row],[Details]:[Details]]=$B35)*(ROW(Table1[[Details]:[Details]])-ROW(Table1[[#Headers],[Details]])),COLUMNS($C$10:C34))),"") | D35: =IF(COLUMNS($C$10:D34)<=$A35,INDEX(Table1[[PARTICULAR]:[PARTICULAR]],_xlfn.AGGREGATE(15,3,(Table1[[#This Row],[Details]:[Details]]=$B35)/(Table1[[#This Row],[Details]:[Details]]=$B35)*(ROW(Table1[[Details]:[Details]])-ROW(Table1[[#Headers],[Details]])),COLUMNS($C$10:D34))),"") | E35: =IF(COLUMNS($C$10:E34)<=$A35,INDEX(Table1[[PARTICULAR]:[PARTICULAR]],_xlfn.AGGREGATE(15,3,(Table1[[#This Row],[Details]:[Details]]=$B35)/(Table1[[#This Row],[Details]:[Details]]=$B35)*(ROW(Table1[[Details]:[Details]])-ROW(Table1[[#Headers],[Details]])),COLUMNS($C$10:E34))),"") | F35: =IF(COLUMNS($C$10:F34)<=$A35,INDEX(Table1[[PARTICULAR]:[PARTICULAR]],_xlfn.AGGREGATE(15,3,(Table1[[#This Row],[Details]:[Details]]=$B35)/(Table1[[#This Row],[Details]:[Details]]=$B35)*(ROW(Table1[[Details]:[Details]])-ROW(Table1[[#Headers],[Details]])),COLUMNS($C$10:F34))),"") | G35: =IF(COLUMNS($C$10:G34)<=$A35,INDEX(Table1[[PARTICULAR]:[PARTICULAR]],_xlfn.AGGREGATE(15,3,(Table1[[#This Row],[Details]:[Details]]=$B35)/(Table1[[#This Row],[Details]:[Details]]=$B35)*(ROW(Table1[[Details]:[Details]])-ROW(Table1[[#Headers],[Details]])),COLUMNS($C$10:G34))),"") | H35: =IF(COLUMNS($C$10:H34)<=$A35,INDEX(Table1[[PARTICULAR]:[PARTICULAR]],_xlfn.AGGREGATE(15,3,(Table1[[#This Row],[Details]:[Details]]=$B35)/(Table1[[#This Row],[Details]:[Details]]=$B35)*(ROW(Table1[[Details]:[Details]])-ROW(Table1[[#Headers],[Details]])),COLUMNS($C$10:H34))),"") | I35: =IF(COLUMNS($C$10:I34)<=$A35,INDEX(Table1[[PARTICULAR]:[PARTICULAR]],_xlfn.AGGREGATE(15,3,(Table1[[#This Row],[Details]:[Details]]=$B35)/(Table1[[#This Row],[Details]:[Details]]=$B35)*(ROW(Table1[[Details]:[Details]])-ROW(Table1[[#Headers],[Details]])),COLUMNS($C$10:I34))),"") | J35: =IF(COLUMNS($C$10:J34)<=$A35,INDEX(Table1[[PARTICULAR]:[PARTICULAR]],_xlfn.AGGREGATE(15,3,(Table1[[#This Row],[Details]:[Details]]=$B35)/(Table1[[#This Row],[Details]:[Details]]=$B35)*(ROW(Table1[[Details]:[Details]])-ROW(Table1[[#Headers],[Details]])),COLUMNS($C$10:J34))),"") | ... CB35: =IF(COLUMNS($C$10:CB34)<=$A35,INDEX(Table1[[PARTICULAR]:[PARTICULAR]],_xlfn.AGGREGATE(15,3,(Table1[[#This Row],[Details]:[Details]]=$B35)/(Table1[[#This Row],[Details]:[Details]]=$B35)*(ROW(Table1[[Details]:[Details]])-ROW(Table1[[#Headers],[Details]])),COLUMNS($C$10:CB34))),"")
B36: =IFERROR(INDEX(Table1[Details],MATCH(0,INDEX(COUNTIF($B$10:B35,Table1[Details]),),0)),"") | C36: =IF(COLUMNS($C$10:C35)<=$A36,INDEX(Table1[[PARTICULAR]:[PARTICULAR]],_xlfn.AGGREGATE(15,3,(Table1[[#This Row],[Details]:[Details]]=$B36)/(Table1[[#This Row],[Details]:[Details]]=$B36)*(ROW(Table1[[Details]:[Details]])-ROW(Table1[[#Headers],[Details]])),COLUMNS($C$10:C35))),"") | D36: =IF(COLUMNS($C$10:D35)<=$A36,INDEX(Table1[[PARTICULAR]:[PARTICULAR]],_xlfn.AGGREGATE(15,3,(Table1[[#This Row],[Details]:[Details]]=$B36)/(Table1[[#This Row],[Details]:[Details]]=$B36)*(ROW(Table1[[Details]:[Details]])-ROW(Table1[[#Headers],[Details]])),COLUMNS($C$10:D35))),"") | E36: =IF(COLUMNS($C$10:E35)<=$A36,INDEX(Table1[[PARTICULAR]:[PARTICULAR]],_xlfn.AGGREGATE(15,3,(Table1[[#This Row],[Details]:[Details]]=$B36)/(Table1[[#This Row],[Details]:[Details]]=$B36)*(ROW(Table1[[Details]:[Details]])-ROW(Table1[[#Headers],[Details]])),COLUMNS($C$10:E35))),"") | F36: =IF(COLUMNS($C$10:F35)<=$A36,INDEX(Table1[[PARTICULAR]:[PARTICULAR]],_xlfn.AGGREGATE(15,3,(Table1[[#This Row],[Details]:[Details]]=$B36)/(Table1[[#This Row],[Details]:[Details]]=$B36)*(ROW(Table1[[Details]:[Details]])-ROW(Table1[[#Headers],[Details]])),COLUMNS($C$10:F35))),"") | G36: =IF(COLUMNS($C$10:G35)<=$A36,INDEX(Table1[[PARTICULAR]:[PARTICULAR]],_xlfn.AGGREGATE(15,3,(Table1[[#This Row],[Details]:[Details]]=$B36)/(Table1[[#This Row],[Details]:[Details]]=$B36)*(ROW(Table1[[Details]:[Details]])-ROW(Table1[[#Headers],[Details]])),COLUMNS($C$10:G35))),"") | H36: =IF(COLUMNS($C$10:H35)<=$A36,INDEX(Table1[[PARTICULAR]:[PARTICULAR]],_xlfn.AGGREGATE(15,3,(Table1[[#This Row],[Details]:[Details]]=$B36)/(Table1[[#This Row],[Details]:[Details]]=$B36)*(ROW(Table1[[Details]:[Details]])-ROW(Table1[[#Headers],[Details]])),COLUMNS($C$10:H35))),"") | I36: =IF(COLUMNS($C$10:I35)<=$A36,INDEX(Table1[[PARTICULAR]:[PARTICULAR]],_xlfn.AGGREGATE(15,3,(Table1[[#This Row],[Details]:[Details]]=$B36)/(Table1[[#This Row],[Details]:[Details]]=$B36)*(ROW(Table1[[Details]:[Details]])-ROW(Table1[[#Headers],[Details]])),COLUMNS($C$10:I35))),"") | J36: =IF(COLUMNS($C$10:J35)<=$A36,INDEX(Table1[[PARTICULAR]:[PARTICULAR]],_xlfn.AGGREGATE(15,3,(Table1[[#This Row],[Details]:[Details]]=$B36)/(Table1[[#This Row],[Details]:[Details]]=$B36)*(ROW(Table1[[Details]:[Details]])-ROW(Table1[[#Headers],[Details]])),COLUMNS($C$10:J35))),"") | ... CB36: =IF(COLUMNS($C$10:CB35)<=$A36,INDEX(Table1[[PARTICULAR]:[PARTICULAR]],_xlfn.AGGREGATE(15,3,(Table1[[#This Row],[Details]:[Details]]=$B36)/(Table1[[#This Row],[Details]:[Details]]=$B36)*(ROW(Table1[[Details]:[Details]])-ROW(Table1[[#Headers],[Details]])),COLUMNS($C$10:CB35))),"")
B37: =IFERROR(INDEX(Table1[Details],MATCH(0,INDEX(COUNTIF($B$10:B36,Table1[Details]),),0)),"") | C37: =IF(COLUMNS($C$10:C36)<=$A37,INDEX(Table1[[PARTICULAR]:[PARTICULAR]],_xlfn.AGGREGATE(15,3,(Table1[[#This Row],[Details]:[Details]]=$B37)/(Table1[[#This Row],[Details]:[Details]]=$B37)*(ROW(Table1[[Details]:[Details]])-ROW(Table1[[#Headers],[Details]])),COLUMNS($C$10:C36))),"") | D37: =IF(COLUMNS($C$10:D36)<=$A37,INDEX(Table1[[PARTICULAR]:[PARTICULAR]],_xlfn.AGGREGATE(15,3,(Table1[[#This Row],[Details]:[Details]]=$B37)/(Table1[[#This Row],[Details]:[Details]]=$B37)*(ROW(Table1[[Details]:[Details]])-ROW(Table1[[#Headers],[Details]])),COLUMNS($C$10:D36))),"") | E37: =IF(COLUMNS($C$10:E36)<=$A37,INDEX(Table1[[PARTICULAR]:[PARTICULAR]],_xlfn.AGGREGATE(15,3,(Table1[[#This Row],[Details]:[Details]]=$B37)/(Table1[[#This Row],[Details]:[Details]]=$B37)*(ROW(Table1[[Details]:[Details]])-ROW(Table1[[#Headers],[Details]])),COLUMNS($C$10:E36))),"") | F37: =IF(COLUMNS($C$10:F36)<=$A37,INDEX(Table1[[PARTICULAR]:[PARTICULAR]],_xlfn.AGGREGATE(15,3,(Table1[[#This Row],[Details]:[Details]]=$B37)/(Table1[[#This Row],[Details]:[Details]]=$B37)*(ROW(Table1[[Details]:[Details]])-ROW(Table1[[#Headers],[Details]])),COLUMNS($C$10:F36))),"") | G37: =IF(COLUMNS($C$10:G36)<=$A37,INDEX(Table1[[PARTICULAR]:[PARTICULAR]],_xlfn.AGGREGATE(15,3,(Table1[[#This Row],[Details]:[Details]]=$B37)/(Table1[[#This Row],[Details]:[Details]]=$B37)*(ROW(Table1[[Details]:[Details]])-ROW(Table1[[#Headers],[Details]])),COLUMNS($C$10:G36))),"") | H37: =IF(COLUMNS($C$10:H36)<=$A37,INDEX(Table1[[PARTICULAR]:[PARTICULAR]],_xlfn.AGGREGATE(15,3,(Table1[[#This Row],[Details]:[Details]]=$B37)/(Table1[[#This Row],[Details]:[Details]]=$B37)*(ROW(Table1[[Details]:[Details]])-ROW(Table1[[#Headers],[Details]])),COLUMNS($C$10:H36))),"") | I37: =IF(COLUMNS($C$10:I36)<=$A37,INDEX(Table1[[PARTICULAR]:[PARTICULAR]],_xlfn.AGGREGATE(15,3,(Table1[[#This Row],[Details]:[Details]]=$B37)/(Table1[[#This Row],[Details]:[Details]]=$B37)*(ROW(Table1[[Details]:[Details]])-ROW(Table1[[#Headers],[Details]])),COLUMNS($C$10:I36))),"") | J37: =IF(COLUMNS($C$10:J36)<=$A37,INDEX(Table1[[PARTICULAR]:[PARTICULAR]],_xlfn.AGGREGATE(15,3,(Table1[[#This Row],[Details]:[Details]]=$B37)/(Table1[[#This Row],[Details]:[Details]]=$B37)*(ROW(Table1[[Details]:[Details]])-ROW(Table1[[#Headers],[Details]])),COLUMNS($C$10:J36))),"") | ... CB37: =IF(COLUMNS($C$10:CB36)<=$A37,INDEX(Table1[[PARTICULAR]:[PARTICULAR]],_xlfn.AGGREGATE(15,3,(Table1[[#This Row],[Details]:[Details]]=$B37)/(Table1[[#This Row],[Details]:[Details]]=$B37)*(ROW(Table1[[Details]:[Details]])-ROW(Table1[[#Headers],[Details]])),COLUMNS($C$10:CB36))),"")
B38: =IFERROR(INDEX(Table1[Details],MATCH(0,INDEX(COUNTIF($B$10:B37,Table1[Details]),),0)),"")
B39: =IFERROR(INDEX(Table1[Details],MATCH(0,INDEX(COUNTIF($B$10:B38,Table1[Details]),),0)),"")
B40: =IFERROR(INDEX(Table1[Details],MATCH(0,INDEX(COUNTIF($B$10:B39,Table1[Details]),),0)),"")
B41: =IFERROR(INDEX(Table1[Details],MATCH(0,INDEX(COUNTIF($B$10:B40,Table1[Details]),),0)),"")
B42: =IFERROR(INDEX(Table1[Details],MATCH(0,INDEX(COUNTIF($B$10:B41,Table1[Details]),),0)),"")
B43: =IFERROR(INDEX(Table1[Details],MATCH(0,INDEX(COUNTIF($B$10:B42,Table1[Details]),),0)),"")
B44: =IFERROR(INDEX(Table1[Details],MATCH(0,INDEX(COUNTIF($B$10:B43,Table1[Details]),),0)),"")
B45: =IFERROR(INDEX(Table1[Details],MATCH(0,INDEX(COUNTIF($B$10:B44,Table1[Details]),),0)),"")
B46: =IFERROR(INDEX(Table1[Details],MATCH(0,INDEX(COUNTIF($B$10:B45,Table1[Details]),),0)),"")
B47: =IFERROR(INDEX(Table1[Details],MATCH(0,INDEX(COUNTIF($B$10:B46,Table1[Details]),),0)),"")
B48: =IFERROR(INDEX(Table1[Details],MATCH(0,INDEX(COUNTIF($B$10:B47,Table1[Details]),),0)),"")
B49: =IFERROR(INDEX(Table1[Details],MATCH(0,INDEX(COUNTIF($B$10:B48,Table1[Details]),),0)),"")
... B102: =IFERROR(INDEX(Table1[Details],MATCH(0,INDEX(COUNTIF($B$10:B101,Table1[Details]),),0)),"")

Sheet Auto PO
A1: Sr No. | B1: Doc. Type | C1: Vendor | D1: Purch.Org | E1: Purch.Group | F1: Site | G1: Short Text | H1: MC | I1: Item Cat | J1: Acct Assgt Cat | K1: GL Account | L1: Cost center | M1: Order Number | N1: Network | O1: Network Item | P1: Service No | Q1: Service Qty | R1: Net Price | S1: Tax Code | T1: Article No | U1: PO Qty | V1: PO Net Price | W1: Purchase Requistion | X1: Purchase Requistion Item | Y1: Campaign Code | Z1: Season | AA1: Campaign Name
A2: 1 | B2: ZVMC | C2: =+'PT ABC'!G$5 -> 7008750 | D2: 1000 | E2: 302 | F2: =+'PT ABC'!M$5 -> 0 | H2: OOTV2V12V | J2: F | K2: 417772 | M2: =F2&"VM2021" -> 0VM2021 | S2: V0 | T2: =+PIVOT!B5 -> 720001707 | U2: =+PIVOT!D5 -> Festive | V2: =+PIVOT!C5 -> 40 | Y2: =+PIVOT!A5 -> FE21/OCT/WINW | Z2: =+PIVOT!D5 -> Festive | AA2: =+PIVOT!E5 -> 0
A3: 1 | B3: ZVMC | C3: =+'PT ABC'!G$5 -> 7008750 | D3: 1000 | E3: 302 | F3: =+'PT ABC'!M$5 -> 0 | H3: OOTV2V12V | J3: F | K3: 417772 | M3: =F3&"VM2021" -> 0VM2021 | S3: V0 | T3: =+PIVOT!B6 -> 720001737 | U3: =+PIVOT!D6 -> Festive | V3: =+PIVOT!C6 -> 15 | Y3: =+PIVOT!A6 -> 0 | Z3: =+PIVOT!D6 -> Festive | AA3: =+PIVOT!E6 -> 0
A4: 1 | B4: ZVMC | C4: =+'PT ABC'!G$5 -> 7008750 | D4: 1000 | E4: 302 | F4: =+'PT ABC'!M$5 -> 0 | H4: OOTV2V12V | J4: F | K4: 417772 | M4: =F4&"VM2021" -> 0VM2021 | S4: V0 | T4: =+PIVOT!B7 -> 720001997 | U4: =+PIVOT!D7 -> Festive | V4: =+PIVOT!C7 -> 25 | Y4: =+PIVOT!A7 -> 0 | Z4: =+PIVOT!D7 -> Festive | AA4: =+PIVOT!E7 -> 0
A5: 1 | B5: ZVMC | C5: =+'PT ABC'!G$5 -> 7008750 | D5: 1000 | E5: 302 | F5: =+'PT ABC'!M$5 -> 0 | H5: OOTV2V12V | J5: F | K5: 417772 | M5: =F5&"VM2021" -> 0VM2021 | S5: V0 | T5: =+PIVOT!B8 -> 720002029 | U5: =+PIVOT!D8 -> Festive | V5: =+PIVOT!C8 -> 25 | Y5: =+PIVOT!A8 -> 0 | Z5: =+PIVOT!D8 -> Festive | AA5: =+PIVOT!E8 -> 0
A6: 1 | B6: ZVMC | C6: =+'PT ABC'!G$5 -> 7008750 | D6: 1000 | E6: 302 | F6: =+'PT ABC'!M$5 -> 0 | H6: OOTV2V12V | J6: F | K6: 417772 | M6: =F6&"VM2021" -> 0VM2021 | S6: V0 | T6: =+PIVOT!B9 -> 720002125 | U6: =+PIVOT!D9 -> Festive | V6: =+PIVOT!C9 -> 5 | Y6: =+PIVOT!A9 -> 0 | Z6: =+PIVOT!D9 -> Festive | AA6: =+PIVOT!E9 -> 0
A7: 1 | B7: ZVMC | C7: =+'PT ABC'!G$5 -> 7008750 | D7: 1000 | E7: 302 | F7: =+'PT ABC'!M$5 -> 0 | H7: OOTV2V12V | J7: F | K7: 417772 | M7: =F7&"VM2021" -> 0VM2021 | S7: V0 | T7: =+PIVOT!B10 -> 720002000 | U7: =+PIVOT!D10 -> Festive | V7: =+PIVOT!C10 -> 58 | Y7: =+PIVOT!A10 -> 0 | Z7: =+PIVOT!D10 -> Festive | AA7: =+PIVOT!E10 -> 0
A8: 1 | B8: ZVMC | C8: =+'PT ABC'!G$5 -> 7008750 | D8: 1000 | E8: 302 | F8: =+'PT ABC'!M$5 -> 0 | H8: OOTV2V12V | J8: F | K8: 417772 | M8: =F8&"VM2021" -> 0VM2021 | S8: V0 | T8: =+PIVOT!B11 -> 720001567 | U8: =+PIVOT!D11 -> Festive | V8: =+PIVOT!C11 -> 60 | Y8: =+PIVOT!A11 -> 0 | Z8: =+PIVOT!D11 -> Festive | AA8: =+PIVOT!E11 -> 0
A9: 1 | B9: ZVMC | C9: =+'PT ABC'!G$5 -> 7008750 | D9: 1000 | E9: 302 | F9: =+'PT ABC'!M$5 -> 0 | H9: OOTV2V12V | J9: F | K9: 417772 | M9: =F9&"VM2021" -> 0VM2021 | S9: V0 | T9: =+PIVOT!B12 -> 720001999 | U9: =+PIVOT!D12 -> Festive | V9: =+PIVOT!C12 -> 49 | Y9: =+PIVOT!A12 -> 0 | Z9: =+PIVOT!D12 -> Festive | AA9: =+PIVOT!E12 -> 0
A10: 1 | B10: ZVMC | C10: =+'PT ABC'!G$5 -> 7008750 | D10: 1000 | E10: 302 | F10: =+'PT ABC'!M$5 -> 0 | H10: OOTV2V12V | J10: F | K10: 417772 | M10: =F10&"VM2021" -> 0VM2021 | S10: V0 | T10: =+PIVOT!B13 -> 720002125 | U10: =+PIVOT!D13 -> Festive | V10: =+PIVOT!C13 -> 5 | Y10: =+PIVOT!A13 -> FE21/OCT/WIN | Z10: =+PIVOT!D13 -> Festive | AA10: =+PIVOT!E13 -> 0
A11: 1 | B11: ZVMC | C11: =+'PT ABC'!G$5 -> 7008750 | D11: 1000 | E11: 302 | F11: =+'PT ABC'!M$5 -> 0 | H11: OOTV2V12V | J11: F | K11: 417772 | M11: =F11&"VM2021" -> 0VM2021 | S11: V0 | T11: =+PIVOT!B14 -> 720001567 | U11: =+PIVOT!D14 -> Festive | V11: =+PIVOT!C14 -> 60 | Y11: =+PIVOT!A14 -> 0 | Z11: =+PIVOT!D14 -> Festive | AA11: =+PIVOT!E14 -> 0
A12: 1 | B12: ZVMC | C12: =+'PT ABC'!G$5 -> 7008750 | D12: 1000 | E12: 302 | F12: =+'PT ABC'!M$5 -> 0 | H12: OOTV2V12V | J12: F | K12: 417772 | M12: =F12&"VM2021" -> 0VM2021 | S12: V0 | T12: =+PIVOT!B15 -> 720002035 | U12: =+PIVOT!D15 -> Festive | V12: =+PIVOT!C15 -> (blank) | Y12: =+PIVOT!A15 -> 0 | Z12: =+PIVOT!D15 -> Festive | AA12: =+PIVOT!E15 -> 0
A13: 1 | B13: ZVMC | C13: =+'PT ABC'!G$5 -> 7008750 | D13: 1000 | E13: 302 | F13: =+'PT ABC'!M$5 -> 0 | H13: OOTV2V12V | J13: F | K13: 417772 | M13: =F13&"VM2021" -> 0VM2021 | S13: V0 | T13: =+PIVOT!B16 -> (blank) | U13: =+PIVOT!D16 -> Festive | V13: =+PIVOT!C16 -> (blank) | Y13: =+PIVOT!A16 -> 0 | Z13: =+PIVOT!D16 -> Festive | AA13: =+PIVOT!E16 -> 0
... A33: 1 | B33: ZVMC | C33: =+'PT ABC'!G$5 -> 7008750 | D33: 1000 | E33: 302 | F33: =+'PT ABC'!M$5 -> 0 | H33: OOTV2V12V | J33: F | K33: 417772 | M33: =F33&"VM2021" -> 0VM2021 | S33: V0 | T33: =+PIVOT!B36 -> 0 | U33: =+PIVOT!D36 -> 0 | V33: =+PIVOT!C36 -> 0 | Y33: =+PIVOT!A36 -> 0 | Z33: =+PIVOT!D36 -> 0 | AA33: =+PIVOT!E36 -> 0

Sheet PIVOT
E3: Values
A4: Campaign Code | B4: Article | C4: Rate | D4: Season | E4: Sum of Total SQFT | F4: Sum of Amount | G4: Sum of Total
A5: FE21/OCT/WINW | B5: 720001707 | C5: 40 | D5: Festive | E5: 0 | F5: 0 | G5: 0
B6: 720001737 | C6: 15 | D6: Festive | E6: 0 | F6: 0 | G6: 0
B7: 720001997 | C7: 25 | D7: Festive | E7: 0 | F7: 0 | G7: 0
B8: 720002029 | C8: 25 | D8: Festive | E8: 0 | F8: 0 | G8: 0
B9: 720002125 | C9: 5 | D9: Festive | E9: 0 | F9: 0 | G9: 0
B10: 720002000 | C10: 58 | D10: Festive | E10: 0 | F10: 0 | G10: 0
B11: 720001567 | C11: 60 | D11: Festive | E11: 0 | F11: 0 | G11: 0
B12: 720001999 | C12: 49 | D12: Festive | E12: 0 | F12: 0 | G12: 0
A13: FE21/OCT/WIN | B13: 720002125 | C13: 5 | D13: Festive | E13: 0 | F13: 0 | G13: 0
B14: 720001567 | C14: 60 | D14: Festive | E14: 0 | F14: 0 | G14: 0
B15: 720002035 | C15: (blank) | D15: Festive | E15: 0 | F15: 0 | G15: 0
B16: (blank) | C16: (blank) | D16: Festive
A17: Grand Total | E17: 0 | F17: 0 | G17: 0

Sheet Auto PO.
A1: Sr No. | B1: Doc. Type | C1: Vendor | D1: Purch.Org | E1: Purch.Group | F1: Site | G1: Short Text | H1: MC | I1: Item Cat | J1: Acct Assgt Cat | K1: GL Account | L1: Cost center | M1: Order Number | N1: Network | O1: Network Item | P1: Service No | Q1: Service Qty | R1: Net Price | S1: Tax Code | T1: Article No | U1: PO Qty | V1: PO Net Price | W1: Purchase Requistion | X1: Purchase Requistion Item | Y1: Campaign Code | Z1: Season | AA1: Campaign Name
A2: 1 | B2: ZVMC | C2: ='PT ABC'!$G$5 -> 7008750 | D2: 1000 | E2: 302 | F2: ='PT ABC'!$M$5 -> 0 | H2: OOTV2V12V | J2: F | K2: 417772 | M2: =F2&"VM2022" -> 0VM2022 | S2: V0 | T2: =Pivot.!D5 -> 720002030 | U2: =Pivot.!F5 -> 0 | V2: =Pivot.!E5 -> 40 | Y2: =Pivot.!A5 -> (blank) | Z2: =Pivot.!B5 -> (blank) | AA2: =Pivot.!C5 -> (blank)
A3: 1 | B3: ZVMC | C3: ='PT ABC'!$G$5 -> 7008750 | D3: 1000 | E3: 302 | F3: ='PT ABC'!$M$5 -> 0 | H3: OOTV2V12V | J3: F | K3: 417772 | M3: =F3&"VM2022" -> 0VM2022 | S3: V0 | T3: =Pivot.!D6 -> 0 | U3: =Pivot.!F6 -> 0 | V3: =Pivot.!E6 -> 0 | Y3: =Pivot.!A6 -> Grand Total | Z3: =Pivot.!B6 -> 0 | AA3: =Pivot.!C6 -> 0
A4: 1 | B4: ZVMC | C4: ='PT ABC'!$G$5 -> 7008750 | D4: 1000 | E4: 302 | F4: ='PT ABC'!$M$5 -> 0 | H4: OOTV2V12V | J4: F | K4: 417772 | M4: =F4&"VM2022" -> 0VM2022 | S4: V0 | T4: =Pivot.!D7 -> 0 | U4: =Pivot.!F7 -> 0 | V4: =Pivot.!E7 -> 0 | Y4: =Pivot.!A7 -> 0 | Z4: =Pivot.!B7 -> 0 | AA4: =Pivot.!C7 -> 0
A5: 1 | B5: ZVMC | C5: ='PT ABC'!$G$5 -> 7008750 | D5: 1000 | E5: 302 | F5: ='PT ABC'!$M$5 -> 0 | H5: OOTV2V12V | J5: F | K5: 417772 | M5: =F5&"VM2022" -> 0VM2022 | S5: V0 | T5: =Pivot.!D8 -> 0 | U5: =Pivot.!F8 -> 0 | V5: =Pivot.!E8 -> 0 | Y5: =Pivot.!A8 -> 0 | Z5: =Pivot.!B8 -> 0 | AA5: =Pivot.!C8 -> 0
A6: 1 | B6: ZVMC | C6: ='PT ABC'!$G$5 -> 7008750 | D6: 1000 | E6: 302 | F6: ='PT ABC'!$M$5 -> 0 | H6: OOTV2V12V | J6: F | K6: 417772 | M6: =F6&"VM2022" -> 0VM2022 | S6: V0 | T6: =Pivot.!D9 -> 0 | U6: =Pivot.!F9 -> 0 | V6: =Pivot.!E9 -> 0 | Y6: =Pivot.!A9 -> 0 | Z6: =Pivot.!B9 -> 0 | AA6: =Pivot.!C9 -> 0
A7: 1 | B7: ZVMC | C7: ='PT ABC'!$G$5 -> 7008750 | D7: 1000 | E7: 302 | F7: ='PT ABC'!$M$5 -> 0 | H7: OOTV2V12V | J7: F | K7: 417772 | M7: =F7&"VM2022" -> 0VM2022 | S7: V0 | T7: =Pivot.!D10 -> 0 | U7: =Pivot.!F10 -> 0 | V7: =Pivot.!E10 -> 0 | Y7: =Pivot.!A10 -> 0 | Z7: =Pivot.!B10 -> 0 | AA7: =Pivot.!C10 -> 0
A8: 1 | B8: ZVMC | C8: ='PT ABC'!$G$5 -> 7008750 | D8: 1000 | E8: 302 | F8: ='PT ABC'!$M$5 -> 0 | H8: OOTV2V12V | J8: F | K8: 417772 | M8: =F8&"VM2022" -> 0VM2022 | S8: V0 | T8: =Pivot.!D11 -> 0 | U8: =Pivot.!F11 -> 0 | V8: =Pivot.!E11 -> 0 | Y8: =Pivot.!A11 -> 0 | Z8: =Pivot.!B11 -> 0 | AA8: =Pivot.!C11 -> 0
A9: 1 | B9: ZVMC | C9: ='PT ABC'!$G$5 -> 7008750 | D9: 1000 | E9: 302 | F9: ='PT ABC'!$M$5 -> 0 | H9: OOTV2V12V | J9: F | K9: 417772 | M9: =F9&"VM2022" -> 0VM2022 | S9: V0 | T9: =Pivot.!D12 -> 0 | U9: =Pivot.!F12 -> 0 | V9: =Pivot.!E12 -> 0 | Y9: =Pivot.!A12 -> 0 | Z9: =Pivot.!B12 -> 0 | AA9: =Pivot.!C12 -> 0
A10: 1 | B10: ZVMC | C10: ='PT ABC'!$G$5 -> 7008750 | D10: 1000 | E10: 302 | F10: ='PT ABC'!$M$5 -> 0 | H10: OOTV2V12V | J10: F | K10: 417772 | M10: =F10&"VM2022" -> 0VM2022 | S10: V0 | T10: =Pivot.!D13 -> 0 | U10: =Pivot.!F13 -> 0 | V10: =Pivot.!E13 -> 0 | Y10: =Pivot.!A13 -> 0 | Z10: =Pivot.!B13 -> 0 | AA10: =Pivot.!C13 -> 0
A11: 1 | B11: ZVMC | C11: ='PT ABC'!$G$5 -> 7008750 | D11: 1000 | E11: 302 | F11: ='PT ABC'!$M$5 -> 0 | H11: OOTV2V12V | J11: F | K11: 417772 | M11: =F11&"VM2022" -> 0VM2022 | S11: V0 | T11: =Pivot.!D14 -> 0 | U11: =Pivot.!F14 -> 0 | V11: =Pivot.!E14 -> 0 | Y11: =Pivot.!A14 -> 0 | Z11: =Pivot.!B14 -> 0 | AA11: =Pivot.!C14 -> 0
A12: 1 | B12: ZVMC | C12: ='PT ABC'!$G$5 -> 7008750 | D12: 1000 | E12: 302 | F12: ='PT ABC'!$M$5 -> 0 | H12: OOTV2V12V | J12: F | K12: 417772 | M12: =F12&"VM2022" -> 0VM2022 | S12: V0 | T12: =Pivot.!D15 -> 0 | U12: =Pivot.!F15 -> 0 | V12: =Pivot.!E15 -> 0 | Y12: =Pivot.!A15 -> 0 | Z12: =Pivot.!B15 -> 0 | AA12: =Pivot.!C15 -> 0
A13: 1 | B13: ZVMC | C13: ='PT ABC'!$G$5 -> 7008750 | D13: 1000 | E13: 302 | F13: ='PT ABC'!$M$5 -> 0 | H13: OOTV2V12V | J13: F | K13: 417772 | M13: =F13&"VM2022" -> 0VM2022 | S13: V0 | T13: =Pivot.!D16 -> 0 | U13: =Pivot.!F16 -> 0 | V13: =Pivot.!E16 -> 0 | Y13: =Pivot.!A16 -> 0 | Z13: =Pivot.!B16 -> 0 | AA13: =Pivot.!C16 -> 0
... A33: 1 | B33: ZVMC | C33: ='PT ABC'!$G$5 -> 7008750 | D33: 1000 | E33: 302 | F33: ='PT ABC'!$M$5 -> 0 | H33: OOTV2V12V | J33: F | K33: 417772 | M33: =F33&"VM2022" -> 0VM2022 | S33: V0 | T33: =Pivot.!D36 -> 0 | U33: =Pivot.!F36 -> 0 | V33: =Pivot.!E36 -> 0 | Y33: =Pivot.!A36 -> 0 | Z33: =Pivot.!B36 -> 0 | AA33: =Pivot.!C36 -> 0

Sheet Pivot.
F3: Values
A4: Campaign Code | B4: Season | C4: Campaign | D4: Article | E4: Rate | F4: Sum of Total SQFT | G4: Sum of Amount | H4: Sum of Total
A5: (blank) | B5: (blank) | C5: (blank) | D5: 720002030 | E5: 40 | F5: 0 | G5: 0 | H5: 0
A6: Grand Total | F6: 0 | G6: 0 | H6: 0

Sheet PT ABC
A1: ADVANCE WORK ORDER ESTIMATE | I1: From :- ABFRL (Pantaloons Division)
A2: To, | K2: Delivery at :- | M2: Within 15 days | O2: Payment at :- | P2: Within 30 days
A3: Vendor Name :- | C3: Transcend Digital Solutions | F3: Contact :- | K3: Store Name :-
A4: Vendor Address :- | K4: Store Address :-
A5: Date | F5: Vendor Code :- | G5: 7008750 | K5: Site Code :-
A6: PO Number :- | F6: Order No :- | K6: Store VM Name :-
A7: AVM Name :- | C7: Shwetali khandelwal | F7: Contact :- | K7: Contact Details :-
A8: Sl. No. | B8: Date | C8: Campaign Code | D8: Particulars | E8: Width (Inch) | F8: Height (Inch) | G8: Quantity | H8: Total SQFT | I8: Details | J8: Description | K8: Rate | L8: Article | M8: Amount | N8: Tax | O8: Tax Amount | P8: Total | Q8: Season | R8: Campaign Name
A9: 1 | G9: 0 | H9: =G9*F9*E9/144 -> 0 | I9: Sunboard | J9: Sun Board 3 mm | K9: =_xlfn.IFNA(VLOOKUP($J9,'Article Master'!$C:$F,4,0),0) -> 18 | L9: =_xlfn.IFNA(VLOOKUP($J9,'Article Master'!$C:$F,2,0),0) -> 720000045 | M9: =K9*H9 -> 0 | N9: =_xlfn.IFNA(VLOOKUP($J9,'Article Master'!$C:$F,3,0),0) -> 0.18 | O9: =N9*M9 -> 0 | P9: =O9+M9 -> 0
A10: =A9+1 -> 2 | G10: 0 | H10: =G10*F10*E10/144 -> 0 | I10: Eco Solvent | J10: Eco Solvent Backlit Print With Lam | K10: =_xlfn.IFNA(VLOOKUP($J10,'Article Master'!$C:$F,4,0),0) -> 45 | L10: =_xlfn.IFNA(VLOOKUP($J10,'Article Master'!$C:$F,2,0),0) -> 720002030 | M10: =K10*H10 -> 0 | N10: =_xlfn.IFNA(VLOOKUP($J10,'Article Master'!$C:$F,3,0),0) -> 0.18 | O10: =N10*M10 -> 0 | P10: =O10+M10 -> 0
A11: =A10+1 -> 3 | G11: 0 | H11: =G11*F11*E11/144 -> 0 | I11: Eco Solvent | J11: Eco Solvent Backlit Print With Lam | K11: =_xlfn.IFNA(VLOOKUP($J11,'Article Master'!$C:$F,4,0),0) -> 45 | L11: =_xlfn.IFNA(VLOOKUP($J11,'Article Master'!$C:$F,2,0),0) -> 720002030 | M11: =K11*H11 -> 0 | N11: =_xlfn.IFNA(VLOOKUP($J11,'Article Master'!$C:$F,3,0),0) -> 0.18 | O11: =N11*M11 -> 0 | P11: =O11+M11 -> 0
A12: =A11+1 -> 4 | G12: 0 | H12: =G12*F12*E12/144 -> 0 | I12: Eco Solvent | J12: Eco Solvent Backlit Print With Lam | K12: =_xlfn.IFNA(VLOOKUP($J12,'Article Master'!$C:$F,4,0),0) -> 45 | L12: =_xlfn.IFNA(VLOOKUP($J12,'Article Master'!$C:$F,2,0),0) -> 720002030 | M12: =K12*H12 -> 0 | N12: =_xlfn.IFNA(VLOOKUP($J12,'Article Master'!$C:$F,3,0),0) -> 0.18 | O12: =N12*M12 -> 0 | P12: =O12+M12 -> 0
A13: =A12+1 -> 5 | G13: 0 | H13: =G13*F13*E13/144 -> 0 | I13: Eco Solvent | J13: Eco Solvent Backlit Print With Lam | K13: =_xlfn.IFNA(VLOOKUP($J13,'Article Master'!$C:$F,4,0),0) -> 45 | L13: =_xlfn.IFNA(VLOOKUP($J13,'Article Master'!$C:$F,2,0),0) -> 720002030 | M13: =K13*H13 -> 0 | N13: =_xlfn.IFNA(VLOOKUP($J13,'Article Master'!$C:$F,3,0),0) -> 0.18 | O13: =N13*M13 -> 0 | P13: =O13+M13 -> 0
A14: =A13+1 -> 6 | G14: 0 | H14: =G14*F14*E14/144 -> 0 | I14: Eco Solvent | J14: Eco Solvent Backlit Print With Lam | K14: =_xlfn.IFNA(VLOOKUP($J14,'Article Master'!$C:$F,4,0),0) -> 45 | L14: =_xlfn.IFNA(VLOOKUP($J14,'Article Master'!$C:$F,2,0),0) -> 720002030 | M14: =K14*H14 -> 0 | N14: =_xlfn.IFNA(VLOOKUP($J14,'Article Master'!$C:$F,3,0),0) -> 0.18 | O14: =N14*M14 -> 0 | P14: =O14+M14 -> 0
A15: =A14+1 -> 7 | G15: 0 | H15: =G15*F15*E15/144 -> 0 | I15: Eco Solvent | J15: Eco Solvent Backlit Print With Lam | K15: =_xlfn.IFNA(VLOOKUP($J15,'Article Master'!$C:$F,4,0),0) -> 45 | L15: =_xlfn.IFNA(VLOOKUP($J15,'Article Master'!$C:$F,2,0),0) -> 720002030 | M15: =K15*H15 -> 0 | N15: =_xlfn.IFNA(VLOOKUP($J15,'Article Master'!$C:$F,3,0),0) -> 0.18 | O15: =N15*M15 -> 0 | P15: =O15+M15 -> 0
A16: =A15+1 -> 8 | G16: 0 | H16: =G16*F16*E16/144 -> 0 | I16: Eco Solvent | J16: Eco Solvent Backlit Print With Lam | K16: =_xlfn.IFNA(VLOOKUP($J16,'Article Master'!$C:$F,4,0),0) -> 45 | L16: =_xlfn.IFNA(VLOOKUP($J16,'Article Master'!$C:$F,2,0),0) -> 720002030 | M16: =K16*H16 -> 0 | N16: =_xlfn.IFNA(VLOOKUP($J16,'Article Master'!$C:$F,3,0),0) -> 0.18 | O16: =N16*M16 -> 0 | P16: =O16+M16 -> 0
A17: =A16+1 -> 9 | G17: 0 | H17: =G17*F17*E17/144 -> 0 | I17: Eco Solvent | J17: Eco Solvent Backlit Print With Lam | K17: =_xlfn.IFNA(VLOOKUP($J17,'Article Master'!$C:$F,4,0),0) -> 45 | L17: =_xlfn.IFNA(VLOOKUP($J17,'Article Master'!$C:$F,2,0),0) -> 720002030 | M17: =K17*H17 -> 0 | N17: =_xlfn.IFNA(VLOOKUP($J17,'Article Master'!$C:$F,3,0),0) -> 0.18 | O17: =N17*M17 -> 0 | P17: =O17+M17 -> 0
A18: =A17+1 -> 10 | G18: 0 | H18: =G18*F18*E18/144 -> 0 | I18: Eco Solvent | J18: Eco Solvent Backlit Print With Lam | K18: =_xlfn.IFNA(VLOOKUP($J18,'Article Master'!$C:$F,4,0),0) -> 45 | L18: =_xlfn.IFNA(VLOOKUP($J18,'Article Master'!$C:$F,2,0),0) -> 720002030 | M18: =K18*H18 -> 0 | N18: =_xlfn.IFNA(VLOOKUP($J18,'Article Master'!$C:$F,3,0),0) -> 0.18 | O18: =N18*M18 -> 0 | P18: =O18+M18 -> 0
A19: =A18+1 -> 11 | G19: 0 | H19: =G19*F19*E19/144 -> 0 | I19: Eco Solvent | J19: Eco Solvent Backlit Print With Lam | K19: =_xlfn.IFNA(VLOOKUP($J19,'Article Master'!$C:$F,4,0),0) -> 45 | L19: =_xlfn.IFNA(VLOOKUP($J19,'Article Master'!$C:$F,2,0),0) -> 720002030 | M19: =K19*H19 -> 0 | N19: =_xlfn.IFNA(VLOOKUP($J19,'Article Master'!$C:$F,3,0),0) -> 0.18 | O19: =N19*M19 -> 0 | P19: =O19+M19 -> 0
A20: =A19+1 -> 12 | G20: 0 | H20: =G20*F20*E20/144 -> 0 | I20: Eco Solvent | J20: Eco Solvent Backlit Print With Lam | K20: =_xlfn.IFNA(VLOOKUP($J20,'Article Master'!$C:$F,4,0),0) -> 45 | L20: =_xlfn.IFNA(VLOOKUP($J20,'Article Master'!$C:$F,2,0),0) -> 720002030 | M20: =K20*H20 -> 0 | N20: =_xlfn.IFNA(VLOOKUP($J20,'Article Master'!$C:$F,3,0),0) -> 0.18 | O20: =N20*M20 -> 0 | P20: =O20+M20 -> 0
A21: =A20+1 -> 13 | G21: 0 | H21: =G21*F21*E21/144 -> 0 | I21: Eco Solvent | J21: Eco Solvent Backlit Print With Lam | K21: =_xlfn.IFNA(VLOOKUP($J21,'Article Master'!$C:$F,4,0),0) -> 45 | L21: =_xlfn.IFNA(VLOOKUP($J21,'Article Master'!$C:$F,2,0),0) -> 720002030 | M21: =K21*H21 -> 0 | N21: =_xlfn.IFNA(VLOOKUP($J21,'Article Master'!$C:$F,3,0),0) -> 0.18 | O21: =N21*M21 -> 0 | P21: =O21+M21 -> 0
... A43: =A42+1 -> 35 | G43: 0 | H43: =G43*F43*E43/144 -> 0 | I43: Eco Solvent | J43: Eco Solvent Backlit Print With Lam | K43: =_xlfn.IFNA(VLOOKUP($J43,'Article Master'!$C:$F,4,0),0) -> 45 | L43: =_xlfn.IFNA(VLOOKUP($J43,'Article Master'!$C:$F,2,0),0) -> 720002030 | M43: =K43*H43 -> 0 | N43: =_xlfn.IFNA(VLOOKUP($J43,'Article Master'!$C:$F,3,0),0) -> 0.18 | O43: =N43*M43 -> 0 | P43: =O43+M43 -> 0
A44: GRAND TOTAL | M44: =SUM(M9:M43) -> 0 | O44: =SUM(O9:O43) -> 0 | P44: =SUM(P9:P43) -> 0

Sheet Sheet2
A1: Sr No. | B1: Doc. Type | C1: Vendor | D1: Purch.Org | E1: Purch.Group | F1: Site | G1: Short Text | H1: MC | I1: Item Cat | J1: Acct Assgt Cat | K1: GL Account | L1: Order Number | M1: Service No | N1: Service Qty | O1: Net Price | P1: Tax Code | Q1: Article No | R1: PO Qty | S1: PO Net Price | T1: Campaign | U1: Pricing Note | V1: Header Note | W1: Term of Payment | X1: Term of Delivery
B2: Hard Coded | C2: Mandatory | D2: Hard coded | E2: Hard coded | F2: Mandatory | G2: Mandatory | H2: Service MC to be hard coded for MC | I2: Mandatory | J2: Mandatory | K2: Hard Coded | L2: Mandatory | M2: Mandatory | N2: Mandatory | O2: Mandatory | P2: Hard Coded | Q2: Mandatory | R2: Mandatory | S2: Mandatory | T2: Mandatory | U2: Mandatory | V2: Mandatory | W2: Mandatory | X2: Mandatory
A3: 1 | B3: ZVMC | C3: ='PT ABC'!G$5 -> 7008750 | D3: 1000 | E3: 302 | F3: ='PT ABC'!M$5 -> 0 | G3: =IF(M3="","",'PT ABC'!I9) | H3: OOTV2V12V | I3: =IF(M3="","","D") | J3: F | K3: 417772 | L3: =F3&'PT ABC'!O$5 -> 0 | M3: =IF(100000000-'PT ABC'!L9>0,'PT ABC'!L9,"") | N3: =IF(M3="","",'PT ABC'!H9) | O3: =IF(M3="","",'PT ABC'!M9) | P3: V0 | Q3: =IF(100000000-'PT ABC'!L9<0,'PT ABC'!L9,"") -> 720000045 | R3: =IF(Q3="","",'PT ABC'!H9) -> 0 | S3: =IF(Q3="","",'PT ABC'!M9) -> 0 | T3: ='PT ABC'!C9 -> 0 | V3: ='PT ABC'!M$5&" "&'PT ABC'!M$3 | W3: ='PT ABC'!O$2 -> Payment at :- | X3: ='PT ABC'!M$2 -> Within 15 days
A4: 1 | B4: ZVMC | C4: ='PT ABC'!G$5 -> 7008750 | D4: 1000 | E4: 302 | F4: ='PT ABC'!M$5 -> 0 | G4: =IF(M4="","",'PT ABC'!I10) | H4: OOTV2V12V | I4: =IF(M4="","","D") | J4: F | K4: 417772 | L4: =F4&'PT ABC'!O$5 -> 0 | M4: =IF(100000000-'PT ABC'!L10>0,'PT ABC'!L10,"") | N4: =IF(M4="","",'PT ABC'!H10) | O4: =IF(M4="","",'PT ABC'!M10) | P4: V0 | Q4: =IF(100000000-'PT ABC'!L10<0,'PT ABC'!L10,"") -> 720002030 | R4: =IF(Q4="","",'PT ABC'!H10) -> 0 | S4: =IF(Q4="","",'PT ABC'!M10) -> 0 | T4: ='PT ABC'!C10 -> 0 | V4: ='PT ABC'!M$5&" "&'PT ABC'!M$3 | W4: ='PT ABC'!O$2 -> Payment at :- | X4: ='PT ABC'!M$2 -> Within 15 days
A5: 1 | B5: ZVMC | C5: ='PT ABC'!G$5 -> 7008750 | D5: 1000 | E5: 302 | F5: ='PT ABC'!M$5 -> 0 | G5: =IF(M5="","",'PT ABC'!I11) | H5: OOTV2V12V | I5: =IF(M5="","","D") | J5: F | K5: 417772 | L5: =F5&'PT ABC'!O$5 -> 0 | M5: =IF(100000000-'PT ABC'!L11>0,'PT ABC'!L11,"") | N5: =IF(M5="","",'PT ABC'!H11) | O5: =IF(M5="","",'PT ABC'!M11) | P5: V0 | Q5: =IF(100000000-'PT ABC'!L11<0,'PT ABC'!L11,"") -> 720002030 | R5: =IF(Q5="","",'PT ABC'!H11) -> 0 | S5: =IF(Q5="","",'PT ABC'!M11) -> 0 | T5: ='PT ABC'!C11 -> 0 | V5: ='PT ABC'!M$5&" "&'PT ABC'!M$3 | W5: ='PT ABC'!O$2 -> Payment at :- | X5: ='PT ABC'!M$2 -> Within 15 days
A6: 1 | B6: ZVMC | C6: ='PT ABC'!G$5 -> 7008750 | D6: 1000 | E6: 302 | F6: ='PT ABC'!M$5 -> 0 | G6: =IF(M6="","",'PT ABC'!I12) | H6: OOTV2V12V | I6: =IF(M6="","","D") | J6: F | K6: 417772 | L6: =F6&'PT ABC'!O$5 -> 0 | M6: =IF(100000000-'PT ABC'!L12>0,'PT ABC'!L12,"") | N6: =IF(M6="","",'PT ABC'!H12) | O6: =IF(M6="","",'PT ABC'!M12) | P6: V0 | Q6: =IF(100000000-'PT ABC'!L12<0,'PT ABC'!L12,"") -> 720002030 | R6: =IF(Q6="","",'PT ABC'!H12) -> 0 | S6: =IF(Q6="","",'PT ABC'!M12) -> 0 | T6: ='PT ABC'!C12 -> 0 | V6: ='PT ABC'!M$5&" "&'PT ABC'!M$3 | W6: ='PT ABC'!O$2 -> Payment at :- | X6: ='PT ABC'!M$2 -> Within 15 days
A7: 1 | B7: ZVMC | C7: ='PT ABC'!G$5 -> 7008750 | D7: 1000 | E7: 302 | F7: ='PT ABC'!M$5 -> 0 | G7: =IF(M7="","",'PT ABC'!I13) | H7: OOTV2V12V | I7: =IF(M7="","","D") | J7: F | K7: 417772 | L7: =F7&'PT ABC'!O$5 -> 0 | M7: =IF(100000000-'PT ABC'!L13>0,'PT ABC'!L13,"") | N7: =IF(M7="","",'PT ABC'!H13) | O7: =IF(M7="","",'PT ABC'!M13) | P7: V0 | Q7: =IF(100000000-'PT ABC'!L13<0,'PT ABC'!L13,"") -> 720002030 | R7: =IF(Q7="","",'PT ABC'!H13) -> 0 | S7: =IF(Q7="","",'PT ABC'!M13) -> 0 | T7: ='PT ABC'!C13 -> 0 | V7: ='PT ABC'!M$5&" "&'PT ABC'!M$3 | W7: ='PT ABC'!O$2 -> Payment at :- | X7: ='PT ABC'!M$2 -> Within 15 days
A8: 1 | B8: ZVMC | C8: ='PT ABC'!G$5 -> 7008750 | D8: 1000 | E8: 302 | F8: ='PT ABC'!M$5 -> 0 | G8: =IF(M8="","",'PT ABC'!I14) | H8: OOTV2V12V | I8: =IF(M8="","","D") | J8: F | K8: 417772 | L8: =F8&'PT ABC'!O$5 -> 0 | M8: =IF(100000000-'PT ABC'!L14>0,'PT ABC'!L14,"") | N8: =IF(M8="","",'PT ABC'!H14) | O8: =IF(M8="","",'PT ABC'!M14) | P8: V0 | Q8: =IF(100000000-'PT ABC'!L14<0,'PT ABC'!L14,"") -> 720002030 | R8: =IF(Q8="","",'PT ABC'!H14) -> 0 | S8: =IF(Q8="","",'PT ABC'!M14) -> 0 | T8: ='PT ABC'!C14 -> 0 | V8: ='PT ABC'!M$5&" "&'PT ABC'!M$3 | W8: ='PT ABC'!O$2 -> Payment at :- | X8: ='PT ABC'!M$2 -> Within 15 days
A9: 1 | B9: ZVMC | C9: ='PT ABC'!G$5 -> 7008750 | D9: 1000 | E9: 302 | F9: ='PT ABC'!M$5 -> 0 | G9: =IF(M9="","",'PT ABC'!I15) | H9: OOTV2V12V | I9: =IF(M9="","","D") | J9: F | K9: 417772 | L9: =F9&'PT ABC'!O$5 -> 0 | M9: =IF(100000000-'PT ABC'!L15>0,'PT ABC'!L15,"") | N9: =IF(M9="","",'PT ABC'!H15) | O9: =IF(M9="","",'PT ABC'!M15) | P9: V0 | Q9: =IF(100000000-'PT ABC'!L15<0,'PT ABC'!L15,"") -> 720002030 | R9: =IF(Q9="","",'PT ABC'!H15) -> 0 | S9: =IF(Q9="","",'PT ABC'!M15) -> 0 | T9: ='PT ABC'!C15 -> 0 | V9: ='PT ABC'!M$5&" "&'PT ABC'!M$3 | W9: ='PT ABC'!O$2 -> Payment at :- | X9: ='PT ABC'!M$2 -> Within 15 days
A10: 1 | B10: ZVMC | C10: ='PT ABC'!G$5 -> 7008750 | D10: 1000 | E10: 302 | F10: ='PT ABC'!M$5 -> 0 | G10: =IF(M10="","",'PT ABC'!#REF!) -> #REF! | H10: OOTV2V12V | I10: =IF(M10="","","D") -> #REF! | J10: F | K10: 417772 | L10: =F10&'PT ABC'!O$5 -> 0 | M10: =IF(100000000-'PT ABC'!#REF!>0,'PT ABC'!#REF!,"") -> #REF! | N10: =IF(M10="","",'PT ABC'!#REF!) -> #REF! | O10: =IF(M10="","",'PT ABC'!#REF!) -> #REF! | P10: V0 | Q10: =IF(100000000-'PT ABC'!#REF!<0,'PT ABC'!#REF!,"") -> #REF! | R10: =IF(Q10="","",'PT ABC'!#REF!) -> #REF! | S10: =IF(Q10="","",'PT ABC'!#REF!) -> #REF! | T10: ='PT ABC'!#REF! -> #REF! | V10: ='PT ABC'!M$5&" "&'PT ABC'!M$3 | W10: ='PT ABC'!O$2 -> Payment at :- | X10: ='PT ABC'!M$2 -> Within 15 days
A11: 1 | B11: ZVMC | C11: ='PT ABC'!G$5 -> 7008750 | D11: 1000 | E11: 302 | F11: ='PT ABC'!M$5 -> 0 | G11: =IF(M11="","",'PT ABC'!#REF!) -> #REF! | H11: OOTV2V12V | I11: =IF(M11="","","D") -> #REF! | J11: F | K11: 417772 | L11: =F11&'PT ABC'!O$5 -> 0 | M11: =IF(100000000-'PT ABC'!#REF!>0,'PT ABC'!#REF!,"") -> #REF! | N11: =IF(M11="","",'PT ABC'!#REF!) -> #REF! | O11: =IF(M11="","",'PT ABC'!#REF!) -> #REF! | P11: V0 | Q11: =IF(100000000-'PT ABC'!#REF!<0,'PT ABC'!#REF!,"") -> #REF! | R11: =IF(Q11="","",'PT ABC'!#REF!) -> #REF! | S11: =IF(Q11="","",'PT ABC'!#REF!) -> #REF! | T11: ='PT ABC'!#REF! -> #REF! | V11: ='PT ABC'!M$5&" "&'PT ABC'!M$3 | W11: ='PT ABC'!O$2 -> Payment at :- | X11: ='PT ABC'!M$2 -> Within 15 days
A12: 1 | B12: ZVMC | C12: ='PT ABC'!G$5 -> 7008750 | D12: 1000 | E12: 302 | F12: ='PT ABC'!M$5 -> 0 | G12: =IF(M12="","",'PT ABC'!#REF!) -> #REF! | H12: OOTV2V12V | I12: =IF(M12="","","D") -> #REF! | J12: F | K12: 417772 | L12: =F12&'PT ABC'!O$5 -> 0 | M12: =IF(100000000-'PT ABC'!#REF!>0,'PT ABC'!#REF!,"") -> #REF! | N12: =IF(M12="","",'PT ABC'!#REF!) -> #REF! | O12: =IF(M12="","",'PT ABC'!#REF!) -> #REF! | P12: V0 | Q12: =IF(100000000-'PT ABC'!#REF!<0,'PT ABC'!#REF!,"") -> #REF! | R12: =IF(Q12="","",'PT ABC'!#REF!) -> #REF! | S12: =IF(Q12="","",'PT ABC'!#REF!) -> #REF! | T12: ='PT ABC'!#REF! -> #REF! | V12: ='PT ABC'!M$5&" "&'PT ABC'!M$3 | W12: ='PT ABC'!O$2 -> Payment at :- | X12: ='PT ABC'!M$2 -> Within 15 days
A13: 1 | B13: ZVMC | C13: ='PT ABC'!G$5 -> 7008750 | D13: 1000 | E13: 302 | F13: ='PT ABC'!M$5 -> 0 | G13: =IF(M13="","",'PT ABC'!#REF!) -> #REF! | H13: OOTV2V12V | I13: =IF(M13="","","D") -> #REF! | J13: F | K13: 417772 | L13: =F13&'PT ABC'!O$5 -> 0 | M13: =IF(100000000-'PT ABC'!#REF!>0,'PT ABC'!#REF!,"") -> #REF! | N13: =IF(M13="","",'PT ABC'!#REF!) -> #REF! | O13: =IF(M13="","",'PT ABC'!#REF!) -> #REF! | P13: V0 | Q13: =IF(100000000-'PT ABC'!#REF!<0,'PT ABC'!#REF!,"") -> #REF! | R13: =IF(Q13="","",'PT ABC'!#REF!) -> #REF! | S13: =IF(Q13="","",'PT ABC'!#REF!) -> #REF! | T13: ='PT ABC'!#REF! -> #REF! | V13: ='PT ABC'!M$5&" "&'PT ABC'!M$3 | W13: ='PT ABC'!O$2 -> Payment at :- | X13: ='PT ABC'!M$2 -> Within 15 days
A14: 1 | B14: ZVMC | C14: ='PT ABC'!G$5 -> 7008750 | D14: 1000 | E14: 302 | F14: ='PT ABC'!M$5 -> 0 | G14: =IF(M14="","",'PT ABC'!#REF!) -> #REF! | H14: OOTV2V12V | I14: =IF(M14="","","D") -> #REF! | J14: F | K14: 417772 | L14: =F14&'PT ABC'!O$5 -> 0 | M14: =IF(100000000-'PT ABC'!#REF!>0,'PT ABC'!#REF!,"") -> #REF! | N14: =IF(M14="","",'PT ABC'!#REF!) -> #REF! | O14: =IF(M14="","",'PT ABC'!#REF!) -> #REF! | P14: V0 | Q14: =IF(100000000-'PT ABC'!#REF!<0,'PT ABC'!#REF!,"") -> #REF! | R14: =IF(Q14="","",'PT ABC'!#REF!) -> #REF! | S14: =IF(Q14="","",'PT ABC'!#REF!) -> #REF! | T14: ='PT ABC'!#REF! -> #REF! | V14: ='PT ABC'!M$5&" "&'PT ABC'!M$3 | W14: ='PT ABC'!O$2 -> Payment at :- | X14: ='PT ABC'!M$2 -> Within 15 days
A15: 1 | B15: ZVMC | C15: ='PT ABC'!G$5 -> 7008750 | D15: 1000 | E15: 302 | F15: ='PT ABC'!M$5 -> 0 | G15: =IF(M15="","",'PT ABC'!#REF!) -> #REF! | H15: OOTV2V12V | I15: =IF(M15="","","D") -> #REF! | J15: F | K15: 417772 | L15: =F15&'PT ABC'!O$5 -> 0 | M15: =IF(100000000-'PT ABC'!#REF!>0,'PT ABC'!#REF!,"") -> #REF! | N15: =IF(M15="","",'PT ABC'!#REF!) -> #REF! | O15: =IF(M15="","",'PT ABC'!#REF!) -> #REF! | P15: V0 | Q15: =IF(100000000-'PT ABC'!#REF!<0,'PT ABC'!#REF!,"") -> #REF! | R15: =IF(Q15="","",'PT ABC'!#REF!) -> #REF! | S15: =IF(Q15="","",'PT ABC'!#REF!) -> #REF! | T15: ='PT ABC'!#REF! -> #REF! | V15: ='PT ABC'!M$5&" "&'PT ABC'!M$3 | W15: ='PT ABC'!O$2 -> Payment at :- | X15: ='PT ABC'!M$2 -> Within 15 days
A16: 1 | B16: ZVMC | C16: ='PT ABC'!G$5 -> 7008750 | D16: 1000 | E16: 302 | F16: ='PT ABC'!M$5 -> 0 | G16: =IF(M16="","",'PT ABC'!#REF!) -> #REF! | H16: OOTV2V12V | I16: =IF(M16="","","D") -> #REF! | J16: F | K16: 417772 | L16: =F16&'PT ABC'!O$5 -> 0 | M16: =IF(100000000-'PT ABC'!#REF!>0,'PT ABC'!#REF!,"") -> #REF! | N16: =IF(M16="","",'PT ABC'!#REF!) -> #REF! | O16: =IF(M16="","",'PT ABC'!#REF!) -> #REF! | P16: V0 | Q16: =IF(100000000-'PT ABC'!#REF!<0,'PT ABC'!#REF!,"") -> #REF! | R16: =IF(Q16="","",'PT ABC'!#REF!) -> #REF! | S16: =IF(Q16="","",'PT ABC'!#REF!) -> #REF! | T16: ='PT ABC'!#REF! -> #REF! | V16: ='PT ABC'!M$5&" "&'PT ABC'!M$3 | W16: ='PT ABC'!O$2 -> Payment at :- | X16: ='PT ABC'!M$2 -> Within 15 days
A17: 1 | B17: ZVMC | C17: ='PT ABC'!G$5 -> 7008750 | D17: 1000 | E17: 302 | F17: ='PT ABC'!M$5 -> 0 | G17: =IF(M17="","",'PT ABC'!#REF!) -> #REF! | H17: OOTV2V12V | I17: =IF(M17="","","D") -> #REF! | J17: F | K17: 417772 | L17: =F17&'PT ABC'!O$5 -> 0 | M17: =IF(100000000-'PT ABC'!#REF!>0,'PT ABC'!#REF!,"") -> #REF! | N17: =IF(M17="","",'PT ABC'!#REF!) -> #REF! | O17: =IF(M17="","",'PT ABC'!#REF!) -> #REF! | P17: V0 | Q17: =IF(100000000-'PT ABC'!#REF!<0,'PT ABC'!#REF!,"") -> #REF! | R17: =IF(Q17="","",'PT ABC'!#REF!) -> #REF! | S17: =IF(Q17="","",'PT ABC'!#REF!) -> #REF! | T17: ='PT ABC'!#REF! -> #REF! | V17: ='PT ABC'!M$5&" "&'PT ABC'!M$3 | W17: ='PT ABC'!O$2 -> Payment at :- | X17: ='PT ABC'!M$2 -> Within 15 days
A18: 1 | B18: ZVMC | C18: ='PT ABC'!G$5 -> 7008750 | D18: 1000 | E18: 302 | F18: ='PT ABC'!M$5 -> 0 | G18: =IF(M18="","",'PT ABC'!#REF!) -> #REF! | H18: OOTV2V12V | I18: =IF(M18="","","D") -> #REF! | J18: F | K18: 417772 | L18: =F18&'PT ABC'!O$5 -> 0 | M18: =IF(100000000-'PT ABC'!#REF!>0,'PT ABC'!#REF!,"") -> #REF! | N18: =IF(M18="","",'PT ABC'!#REF!) -> #REF! | O18: =IF(M18="","",'PT ABC'!#REF!) -> #REF! | P18: V0 | Q18: =IF(100000000-'PT ABC'!#REF!<0,'PT ABC'!#REF!,"") -> #REF! | R18: =IF(Q18="","",'PT ABC'!#REF!) -> #REF! | S18: =IF(Q18="","",'PT ABC'!#REF!) -> #REF! | T18: ='PT ABC'!#REF! -> #REF! | V18: ='PT ABC'!M$5&" "&'PT ABC'!M$3 | W18: ='PT ABC'!O$2 -> Payment at :- | X18: ='PT ABC'!M$2 -> Within 15 days
A19: 1 | B19: ZVMC | C19: ='PT ABC'!G$5 -> 7008750 | D19: 1000 | E19: 302 | F19: ='PT ABC'!M$5 -> 0 | G19: =IF(M19="","",'PT ABC'!#REF!) -> #REF! | H19: OOTV2V12V | I19: =IF(M19="","","D") -> #REF! | J19: F | K19: 417772 | L19: =F19&'PT ABC'!O$5 -> 0 | M19: =IF(100000000-'PT ABC'!#REF!>0,'PT ABC'!#REF!,"") -> #REF! | N19: =IF(M19="","",'PT ABC'!#REF!) -> #REF! | O19: =IF(M19="","",'PT ABC'!#REF!) -> #REF! | P19: V0 | Q19: =IF(100000000-'PT ABC'!#REF!<0,'PT ABC'!#REF!,"") -> #REF! | R19: =IF(Q19="","",'PT ABC'!#REF!) -> #REF! | S19: =IF(Q19="","",'PT ABC'!#REF!) -> #REF! | T19: ='PT ABC'!#REF! -> #REF! | V19: ='PT ABC'!M$5&" "&'PT ABC'!M$3 | W19: ='PT ABC'!O$2 -> Payment at :- | X19: ='PT ABC'!M$2 -> Within 15 days
A20: 1 | B20: ZVMC | C20: ='PT ABC'!G$5 -> 7008750 | D20: 1000 | E20: 302 | F20: ='PT ABC'!M$5 -> 0 | G20: =IF(M20="","",'PT ABC'!#REF!) -> #REF! | H20: OOTV2V12V | I20: =IF(M20="","","D") -> #REF! | J20: F | K20: 417772 | L20: =F20&'PT ABC'!O$5 -> 0 | M20: =IF(100000000-'PT ABC'!#REF!>0,'PT ABC'!#REF!,"") -> #REF! | N20: =IF(M20="","",'PT ABC'!#REF!) -> #REF! | O20: =IF(M20="","",'PT ABC'!#REF!) -> #REF! | P20: V0 | Q20: =IF(100000000-'PT ABC'!#REF!<0,'PT ABC'!#REF!,"") -> #REF! | R20: =IF(Q20="","",'PT ABC'!#REF!) -> #REF! | S20: =IF(Q20="","",'PT ABC'!#REF!) -> #REF! | T20: ='PT ABC'!#REF! -> #REF! | V20: ='PT ABC'!M$5&" "&'PT ABC'!M$3 | W20: ='PT ABC'!O$2 -> Payment at :- | X20: ='PT ABC'!M$2 -> Within 15 days
A21: 1 | B21: ZVMC | C21: ='PT ABC'!G$5 -> 7008750 | D21: 1000 | E21: 302 | F21: ='PT ABC'!M$5 -> 0 | G21: =IF(M21="","",'PT ABC'!#REF!) -> #REF! | H21: OOTV2V12V | I21: =IF(M21="","","D") -> #REF! | J21: F | K21: 417772 | L21: =F21&'PT ABC'!O$5 -> 0 | M21: =IF(100000000-'PT ABC'!#REF!>0,'PT ABC'!#REF!,"") -> #REF! | N21: =IF(M21="","",'PT ABC'!#REF!) -> #REF! | O21: =IF(M21="","",'PT ABC'!#REF!) -> #REF! | P21: V0 | Q21: =IF(100000000-'PT ABC'!#REF!<0,'PT ABC'!#REF!,"") -> #REF! | R21: =IF(Q21="","",'PT ABC'!#REF!) -> #REF! | S21: =IF(Q21="","",'PT ABC'!#REF!) -> #REF! | T21: ='PT ABC'!#REF! -> #REF! | V21: ='PT ABC'!M$5&" "&'PT ABC'!M$3 | W21: ='PT ABC'!O$2 -> Payment at :- | X21: ='PT ABC'!M$2 -> Within 15 days
... A54: 1 | B54: ZVMC | C54: ='PT ABC'!G$5 -> 7008750 | D54: 1000 | E54: 302 | F54: ='PT ABC'!M$5 -> 0 | G54: =IF(M54="","",'PT ABC'!#REF!) -> #REF! | H54: OOTV2V12V | I54: =IF(M54="","","D") -> #REF! | J54: F | K54: 417772 | L54: =F54&'PT ABC'!O$5 -> 0 | M54: =IF(100000000-'PT ABC'!#REF!>0,'PT ABC'!#REF!,"") -> #REF! | N54: =IF(M54="","",'PT ABC'!#REF!) -> #REF! | O54: =IF(M54="","",'PT ABC'!#REF!) -> #REF! | P54: V0 | Q54: =IF(100000000-'PT ABC'!#REF!<0,'PT ABC'!#REF!,"") -> #REF! | R54: =IF(Q54="","",'PT ABC'!#REF!) -> #REF! | S54: =IF(Q54="","",'PT ABC'!#REF!) -> #REF! | T54: ='PT ABC'!#REF! -> #REF! | V54: ='PT ABC'!M$5&" "&'PT ABC'!M$3 | W54: ='PT ABC'!O$2 -> Payment at :- | X54: ='PT ABC'!M$2 -> Within 15 days
A55: 1 | B55: ZVMC | C55: ='PT ABC'!G$5 -> 7008750 | D55: 1000 | E55: 302 | F55: ='PT ABC'!M$5 -> 0 | G55: =IF(M55="","",'PT ABC'!I44) -> 0 | H55: OOTV2V12V | I55: =IF(M55="","","D") -> D | J55: F | K55: 417772 | L55: =F55&'PT ABC'!O$5 -> 0 | M55: =IF(100000000-'PT ABC'!L44>0,'PT ABC'!L44,"") -> 0 | N55: =IF(M55="","",'PT ABC'!H44) -> 0 | O55: =IF(M55="","",'PT ABC'!M44) -> 0 | P55: V0 | Q55: =IF(100000000-'PT ABC'!L44<0,'PT ABC'!L44,"") | R55: =IF(Q55="","",'PT ABC'!H44) | S55: =IF(Q55="","",'PT ABC'!M44) | T55: ='PT ABC'!C44 -> 0 | V55: ='PT ABC'!M$5&" "&'PT ABC'!M$3 | W55: ='PT ABC'!O$2 -> Payment at :- | X55: ='PT ABC'!M$2 -> Within 15 days
A56: 1 | B56: ZVMC | C56: ='PT ABC'!G$5 -> 7008750 | D56: 1000 | E56: 302 | F56: ='PT ABC'!M$5 -> 0 | G56: =IF(M56="","",'PT ABC'!I45) -> 0 | H56: OOTV2V12V | I56: =IF(M56="","","D") -> D | J56: F | K56: 417772 | L56: =F56&'PT ABC'!O$5 -> 0 | M56: =IF(100000000-'PT ABC'!L45>0,'PT ABC'!L45,"") -> 0 | N56: =IF(M56="","",'PT ABC'!H45) -> 0 | O56: =IF(M56="","",'PT ABC'!M45) -> 0 | P56: V0 | Q56: =IF(100000000-'PT ABC'!L45<0,'PT ABC'!L45,"") | R56: =IF(Q56="","",'PT ABC'!H45) | S56: =IF(Q56="","",'PT ABC'!M45) | T56: ='PT ABC'!C45 -> 0 | V56: ='PT ABC'!M$5&" "&'PT ABC'!M$3 | W56: ='PT ABC'!O$2 -> Payment at :- | X56: ='PT ABC'!M$2 -> Within 15 days
